[
  {
    "title": "The Ultimate Harry Potter Trivia Eve",
    "city": "Bengaluru",
    "date": "Sun, 5 Jul 2026",
    "time": "",
    "venue": "Servira: Bengaluru",
    "price": "349",
    "duration": "",
    "language": "",
    "link": "https://in.bookmyshow.com/plays/the-ultimate-harry-potter-trivia-eve/ET00505539",
    "image": "https://in.bmscdn.com/events/moviecard/ET00505539.jpg",
    "_source": "bms",
    "_city": "Bengaluru"
  },
  {
    "title": "Girish Karnad's NAAGMANDAL",
    "city": "Bengaluru",
    "date": "Sat, 4 Jul 2026 onwards",
    "time": "",
    "venue": "Samarthanam Auditorium-TheatreNama: Bengaluru",
    "price": "300",
    "duration": "",
    "language": "Hindi",
    "link": "https://in.bookmyshow.com/plays/girish-karnad-s-naagmandal/ET00500602",
    "image": "https://in.bmscdn.com/events/moviecard/ET00500602.jpg",
    "_source": "bms",
    "_city": "Bengaluru"
  },
  {
    "title": "By 2 Coffee",
    "city": "Bengaluru",
    "date": "Sat, 4 Jul 2026",
    "time": "",
    "venue": "Ranga Shankara: Bengaluru",
    "price": "200",
    "duration": "",
    "language": "Kannada",
    "link": "https://in.bookmyshow.com/plays/by-2-coffee/ET00343215",
    "image": "https://in.bmscdn.com/events/moviecard/ET00343215.jpg",
    "_source": "bms",
    "_city": "Bengaluru"
  },
  {
    "title": "THEATER WORKSHOP",
    "city": "Bengaluru",
    "date": "Sat, 4 Jul 2026",
    "time": "",
    "venue": "Bloom Creative Zone, Whitefield: Bengaluru",
    "price": "1200",
    "duration": "",
    "language": "English",
    "link": "https://in.bookmyshow.com/plays/theater-workshop/ET00505785",
    "image": "https://in.bmscdn.com/events/moviecard/ET00505785.jpg",
    "_source": "bms",
    "_city": "Bengaluru"
  },
  {
    "title": "PowerPoint Roulette by Improv Lore",
    "city": "Bengaluru",
    "date": "Sun, 5 Jul 2026",
    "time": "",
    "venue": "Underline Center: Bengaluru",
    "price": "399",
    "duration": "",
    "language": "",
    "link": "https://in.bookmyshow.com/plays/powerpoint-roulette-by-improv-lore/ET00496743",
    "image": "https://in.bmscdn.com/events/moviecard/ET00496743.jpg",
    "_source": "bms",
    "_city": "Bengaluru"
  },
  {
    "title": "Waiting for Naseer",
    "city": "Bengaluru",
    "date": "Sun, 5 Jul 2026",
    "time": "",
    "venue": "Alliance Francaise: Bengaluru",
    "price": "399",
    "duration": "",
    "language": "Hindi",
    "link": "https://in.bookmyshow.com/plays/waiting-for-naseer/ET00407868",
    "image": "https://in.bmscdn.com/events/moviecard/ET00407868.jpg",
    "_source": "bms",
    "_city": "Bengaluru"
  },
  {
    "title": "Dangeya Munchina Dinagalu",
    "city": "Bengaluru",
    "date": "Sun, 5 Jul 2026",
    "time": "",
    "venue": "Kalagrama (Backside Bangalore University)",
    "price": "150",
    "duration": "",
    "language": "Kannada",
    "link": "https://in.bookmyshow.com/plays/dangeya-munchina-dinagalu/ET00504436",
    "image": "https://in.bmscdn.com/events/moviecard/ET00504436.jpg",
    "_source": "bms",
    "_city": "Bengaluru"
  },
  {
    "title": "GK Maastarara Pranaya Prasanga",
    "city": "Bengaluru",
    "date": "Sat, 4 Jul 2026",
    "time": "",
    "venue": "Kalagrama: Bengaluru",
    "price": "150",
    "duration": "",
    "language": "Kannada",
    "link": "https://in.bookmyshow.com/plays/gk-maastarara-pranaya-prasanga/ET00364231",
    "image": "https://in.bmscdn.com/events/moviecard/ET00364231.jpg",
    "_source": "bms",
    "_city": "Bengaluru"
  },
  {
    "title": "Royal Indian Theatre's - The Ungodly Disco",
    "city": "Bengaluru",
    "date": "",
    "time": "",
    "venue": "Jagriti Theatre: Whitefield, Bengaluru",
    "price": "500",
    "duration": "",
    "language": "English",
    "link": "https://in.bookmyshow.com/plays/the-ungodly-disco/ET00503003",
    "image": "https://in.bmscdn.com/events/moviecard/ET00503003.jpg",
    "_source": "bms",
    "_city": "Bengaluru"
  },
  {
    "title": "Huttadalli Hutta",
    "city": "Bengaluru",
    "date": "",
    "time": "",
    "venue": "KEA Prabhath Rangamandira: Bengaluru",
    "price": "150",
    "duration": "",
    "language": "Kannada",
    "link": "https://in.bookmyshow.com/plays/huttadalli-hutta/ET00434022",
    "image": "https://in.bmscdn.com/events/moviecard/ET00434022.jpg",
    "_source": "bms",
    "_city": "Bengaluru"
  },
  {
    "title": "Home Rule & Kannadakkobane Kailasam",
    "city": "Bengaluru",
    "date": "",
    "time": "",
    "venue": "KEA Prabhath Rangamandira: Bengaluru",
    "price": "150",
    "duration": "",
    "language": "Kannada",
    "link": "https://in.bookmyshow.com/plays/home-rule-kannadakkobane-kailasam/ET00444016",
    "image": "https://in.bmscdn.com/events/moviecard/ET00444016.jpg",
    "_source": "bms",
    "_city": "Bengaluru"
  },
  {
    "title": "Who Killed Agatha?",
    "city": "Bengaluru",
    "date": "",
    "time": "",
    "venue": "Ranga Shankara: Bengaluru",
    "price": "250",
    "duration": "",
    "language": "English",
    "link": "https://in.bookmyshow.com/plays/who-killed-agatha/ET00399508",
    "image": "https://in.bmscdn.com/events/moviecard/ET00399508.jpg",
    "_source": "bms",
    "_city": "Bengaluru"
  },
  {
    "title": "JOKUMARASWAMY",
    "city": "Bengaluru",
    "date": "",
    "time": "",
    "venue": "Ranga Shankara: Bengaluru",
    "price": "300",
    "duration": "",
    "language": "Kannada",
    "link": "https://in.bookmyshow.com/plays/jokumaraswamy/ET00429468",
    "image": "https://in.bmscdn.com/events/moviecard/ET00429468.jpg",
    "_source": "bms",
    "_city": "Bengaluru"
  }
]