[
  {
    "title": "Tax Free",
    "date": "Fri, 10 Jul",
    "venue": "Blank Canvas: New Delhi",
    "price": "149",
    "genreLine": "Hindi/English",
    "link": "https://in.bookmyshow.com/plays/evam-indrajit/ET00407840",
    "image": "https://assets-in.bmscdn.com/discovery-catalog/events/tr:w-400,h-600,bg-CCCCCC,e-usm-2-2-0.5-0.008:w-400.0,h-660.0,cm-pad_resize,bg-000000,fo-top:l-text,ie-RnJpLCAxMCBKdWw%3D,fs-29,co-FFFFFF,ly-612,lx-24,pa-8_0_0_0,l-end/et00407840-zknkgqnbyh-portrait.jpg",
    "time": "7:00 PM",
    "duration": "1 Hour",
    "language": "Hindi, English",
    "genre": "Blank Canvas: New Delhi"
  },
  {
    "title": "Backless Wife of Kamasutra",
    "date": "Fri, 10 Jul",
    "venue": "Bombay Club: Delhi",
    "price": "2000",
    "genreLine": "English",
    "link": "https://in.bookmyshow.com/plays/backless-wife-of-kamasutra/ET00504748",
    "image": "https://assets-in.bmscdn.com/discovery-catalog/events/tr:w-400,h-600,bg-CCCCCC,e-usm-2-2-0.5-0.008:w-400.0,h-660.0,cm-pad_resize,bg-000000,fo-top:l-text,ie-RnJpLCAxMCBKdWw%3D,fs-29,co-FFFFFF,ly-612,lx-24,pa-8_0_0_0,l-end/et00504748-gwjecmrvwc-portrait.jpg",
    "time": "5:00 PM",
    "duration": "1 hour 30 min",
    "language": "English",
    "genre": "Adult, Classic, Fantasy, Historical, Thriller"
  },
  {
    "title": "Ghalib In New Delhi (Hindi Comedy)",
    "date": "Fri, 10 Jul onwards",
    "venue": "Alliance Francaise: Delhi",
    "price": "150",
    "genreLine": "Hindi",
    "link": "https://in.bookmyshow.com/plays/ghalib-in-new-delhi-hindi-comedy/ET00085401",
    "image": "https://assets-in.bmscdn.com/discovery-catalog/events/tr:w-400,h-600,bg-CCCCCC,e-usm-2-2-0.5-0.008:w-400.0,h-660.0,cm-pad_resize,bg-000000,fo-top:l-text,ie-RnJpLCAxMCBKdWwgb253YXJkcw%3D%3D,fs-29,co-FFFFFF,ly-612,lx-24,pa-8_0_0_0,l-end/et00085401-bxyltrxpcx-portrait.jpg",
    "time": "7:00 PM",
    "duration": "1 hour 45 min",
    "language": "Hindi",
    "genre": "Classic, Comedy, Drama"
  },
  {
    "title": "Pierrots Troupe",
    "date": "Fri, 10 Jul onwards",
    "venue": "Multiple Venues",
    "price": "150",
    "genreLine": "Hindi",
    "link": "https://in.bookmyshow.com/plays/pierrots-troupe/ET00374595",
    "image": "https://assets-in.bmscdn.com/discovery-catalog/events/tr:w-400,h-600,bg-CCCCCC,e-usm-2-2-0.5-0.008:w-400.0,h-660.0,cm-pad_resize,bg-000000,fo-top:l-text,ie-RnJpLCAxMCBKdWwgb253YXJkcw%3D%3D,fs-29,co-FFFFFF,ly-612,lx-24,pa-8_0_0_0,l-end:l-image,i-discovery-catalog@@icons@@bundle-icon-shadow-4x.png,lx-15,ly-15,w-50,l-end/et00374595-tjatfkgaqt-portrait.jpg",
    "time": "",
    "duration": "1 hour 45 min",
    "language": "Hindi",
    "genre": ""
  },
  {
    "title": "CHALTE CHALTE WITH MEENA KUMARI (Musical)",
    "date": "Sat, 11 Jul onwards",
    "venue": "Little Theatre Group (LTG) Auditorium: Delhi",
    "price": "150",
    "genreLine": "Hindi",
    "link": "https://in.bookmyshow.com/plays/chalte-chalte-with-meena-kumari-musical/ET00424638",
    "image": "https://assets-in.bmscdn.com/discovery-catalog/events/tr:w-400,h-600,bg-CCCCCC,e-usm-2-2-0.5-0.008:w-400.0,h-660.0,cm-pad_resize,bg-000000,fo-top:l-text,ie-U2F0LCAxMSBKdWwgb253YXJkcw%3D%3D,fs-29,co-FFFFFF,ly-612,lx-24,pa-8_0_0_0,l-end/et00424638-kvpbnzwubb-portrait.jpg",
    "time": "5:00 PM",
    "duration": "1 hour 20 min",
    "language": "Hindi",
    "genre": "Comedy, Drama, Musical"
  },
  {
    "title": "Tragedy Mein Comedy",
    "date": "Sat, 11 Jul",
    "venue": "The Stein Auditorium, India Habitat Centre: Delhi",
    "price": "200",
    "genreLine": "Hindi",
    "link": "https://in.bookmyshow.com/plays/tragedy-mein-comedy/ET00503819",
    "image": "https://assets-in.bmscdn.com/discovery-catalog/events/tr:w-400,h-600,bg-CCCCCC,e-usm-2-2-0.5-0.008:w-400.0,h-660.0,cm-pad_resize,bg-000000,fo-top:l-text,ie-U2F0LCAxMSBKdWw%3D,fs-29,co-FFFFFF,ly-612,lx-24,pa-8_0_0_0,l-end/et00503819-rlqgemxvmt-portrait.jpg",
    "time": "7:30 PM",
    "duration": "1 hour 20 min",
    "language": "Hindi",
    "genre": "Comedy, Tragedy"
  },
  {
    "title": "Final Solutions",
    "date": "Sat, 11 Jul",
    "venue": "Shri Ram Centre for Performing Arts: Delhi",
    "price": "100",
    "genreLine": "Hindi",
    "link": "https://in.bookmyshow.com/plays/final-solutions/ET00402363",
    "image": "https://assets-in.bmscdn.com/discovery-catalog/events/tr:w-400,h-600,bg-CCCCCC,e-usm-2-2-0.5-0.008:w-400.0,h-660.0,cm-pad_resize,bg-000000,fo-top:l-text,ie-U2F0LCAxMSBKdWw%3D,fs-29,co-FFFFFF,ly-612,lx-24,pa-8_0_0_0,l-end/et00402363-tsgyctfpsg-portrait.jpg",
    "time": "7:00 PM",
    "duration": "1 hour 30 min",
    "language": "Hindi",
    "genre": "All age groups"
  },
  {
    "title": "William & Mary",
    "date": "Sat, 11 Jul",
    "venue": "Alliance Francaise: Delhi",
    "price": "500",
    "genreLine": "Hindi/English",
    "link": "https://in.bookmyshow.com/plays/william-mary/ET00504497",
    "image": "https://assets-in.bmscdn.com/discovery-catalog/events/tr:w-400,h-600,bg-CCCCCC,e-usm-2-2-0.5-0.008:w-400.0,h-660.0,cm-pad_resize,bg-000000,fo-top:l-text,ie-U2F0LCAxMSBKdWw%3D,fs-29,co-FFFFFF,ly-612,lx-24,pa-8_0_0_0,l-end/et00504497-yqtptccexh-portrait.jpg",
    "time": "7:00 PM",
    "duration": "1 hour 20 min",
    "language": "Hindi, English",
    "genre": "Comedy"
  },
  {
    "title": "Akbar The Great Nahin Rahe",
    "date": "Sun, 12 Jul",
    "venue": "Alliance Francaise: Delhi",
    "price": "200",
    "genreLine": "Hindi/English",
    "link": "https://in.bookmyshow.com/plays/akbar-the-great-nahin-rahe/ET00339352",
    "image": "https://assets-in.bmscdn.com/discovery-catalog/events/tr:w-400,h-600,bg-CCCCCC,e-usm-2-2-0.5-0.008:w-400.0,h-660.0,cm-pad_resize,bg-000000,fo-top:l-text,ie-U3VuLCAxMiBKdWw%3D,fs-29,co-FFFFFF,ly-612,lx-24,pa-8_0_0_0,l-end/et00339352-yefuhjjbdm-portrait.jpg",
    "time": "7:00 PM",
    "duration": "1 hour 45 min",
    "language": "Hindi, English",
    "genre": "Comedy, Drama"
  },
  {
    "title": "Saiyan Bhaye Kotwal",
    "date": "Sun, 12 Jul",
    "venue": "Akshara Theatre: Delhi",
    "price": "100",
    "genreLine": "Hindi",
    "link": "https://in.bookmyshow.com/plays/saiyan-bhaye-kotwal/ET00504219",
    "image": "https://assets-in.bmscdn.com/discovery-catalog/events/tr:w-400,h-600,bg-CCCCCC,e-usm-2-2-0.5-0.008:w-400.0,h-660.0,cm-pad_resize,bg-000000,fo-top:l-text,ie-U3VuLCAxMiBKdWw%3D,fs-29,co-FFFFFF,ly-612,lx-24,pa-8_0_0_0,l-end/et00504219-pdrlshzend-portrait.jpg",
    "time": "7:00 PM",
    "duration": "1 hour 30 min",
    "language": "Hindi",
    "genre": "Drama"
  },
  {
    "title": "SYMPHONY OF SINNERS",
    "date": "Sun, 12 Jul",
    "venue": "Shri Ram Centre for Performing Arts: Delhi",
    "price": "250",
    "genreLine": "Hindi",
    "link": "https://in.bookmyshow.com/plays/symphony-of-sinners/ET00501586",
    "image": "https://assets-in.bmscdn.com/discovery-catalog/events/tr:w-400,h-600,bg-CCCCCC,e-usm-2-2-0.5-0.008:w-400.0,h-660.0,cm-pad_resize,bg-000000,fo-top:l-text,ie-U3VuLCAxMiBKdWw%3D,fs-29,co-FFFFFF,ly-612,lx-24,pa-8_0_0_0,l-end/et00501586-wvtdajurjm-portrait.jpg",
    "time": "",
    "duration": "1 hour 20 min",
    "language": "Hindi, Gujarati",
    "genre": ""
  },
  {
    "title": "Dastan - e - Aam",
    "date": "Sun, 12 Jul",
    "venue": "The Quorum: Gurugram",
    "price": "699",
    "genreLine": "Hindi/Urdu",
    "link": "https://in.bookmyshow.com/plays/dastan-e-aam/ET00504486",
    "image": "https://assets-in.bmscdn.com/discovery-catalog/events/tr:w-400,h-600,bg-CCCCCC,e-usm-2-2-0.5-0.008:w-400.0,h-660.0,cm-pad_resize,bg-000000,fo-top:l-text,ie-U3VuLCAxMiBKdWw%3D,fs-29,co-FFFFFF,ly-612,lx-24,pa-8_0_0_0,l-end/et00504486-xzetvqalxr-portrait.jpg",
    "time": "7:00 PM",
    "duration": "1 Hour",
    "language": "Hindi, Urdu",
    "genre": "Drama"
  },
  {
    "title": "Buddha Piprahwa Relics at Qila Rai Pithora Museum",
    "date": "Sun, 12 Jul",
    "venue": "Qila Rai Pithora Fort: Delhi",
    "price": "700",
    "genreLine": "English/Hindi",
    "link": "https://in.bookmyshow.com/plays/buddha-piprahwa-relics-at-qila-rai-pithora-museum/ET00492842",
    "image": "https://assets-in.bmscdn.com/discovery-catalog/events/tr:w-400,h-600,bg-CCCCCC,e-usm-2-2-0.5-0.008:w-400.0,h-660.0,cm-pad_resize,bg-000000,fo-top:l-text,ie-U3VuLCAxMiBKdWw%3D,fs-29,co-FFFFFF,ly-612,lx-24,pa-8_0_0_0,l-end/et00492842-jsujqmzrbk-portrait.jpg",
    "time": "6:00 PM",
    "duration": "2 Hour",
    "language": "English, Hindi",
    "genre": "Biography, Historical, Tribute"
  },
  {
    "title": "A Mystery Called Woman",
    "date": "Sun, 12 Jul onwards",
    "venue": "The Piano Man: Gurugram",
    "price": "199",
    "genreLine": "English",
    "link": "https://in.bookmyshow.com/plays/a-mystery-called-woman/ET00486268",
    "image": "https://assets-in.bmscdn.com/discovery-catalog/events/tr:w-400,h-600,bg-CCCCCC,e-usm-2-2-0.5-0.008:w-400.0,h-660.0,cm-pad_resize,bg-000000,fo-top:l-text,ie-U3VuLCAxMiBKdWwgb253YXJkcw%3D%3D,fs-29,co-FFFFFF,ly-612,lx-24,pa-8_0_0_0,l-end/et00486268-nqwnwwusmu-portrait.jpg",
    "time": "4:45 PM",
    "duration": "1 hour 10 min",
    "language": "English",
    "genre": "All age groups"
  },
  {
    "title": "Khushi equals Solved",
    "date": "Sun, 12 Jul",
    "venue": "The Blank Canvas, LTG Auditorium: Delhi",
    "price": "200",
    "genreLine": "Hinglish",
    "link": "https://in.bookmyshow.com/plays/khushi-equals-solved/ET00465964",
    "image": "https://assets-in.bmscdn.com/discovery-catalog/events/tr:w-400,h-600,bg-CCCCCC,e-usm-2-2-0.5-0.008:w-400.0,h-660.0,cm-pad_resize,bg-000000,fo-top:l-text,ie-U3VuLCAxMiBKdWw%3D,fs-29,co-FFFFFF,ly-612,lx-24,pa-8_0_0_0,l-end/et00465964-rqnvfmgpxy-portrait.jpg",
    "time": "12:00 PM",
    "duration": "1 hour 10 min",
    "language": "Marathi",
    "genre": "Hinglish"
  },
  {
    "title": "Dostana Poetry Show",
    "date": "Sun, 12 Jul",
    "venue": "Decent Studio - Block D: Noida",
    "price": "199",
    "genreLine": "Hindi/Urdu",
    "link": "https://in.bookmyshow.com/plays/dostana-poetry-show/ET00505151",
    "image": "https://assets-in.bmscdn.com/discovery-catalog/events/tr:w-400,h-600,bg-CCCCCC,e-usm-2-2-0.5-0.008:w-400.0,h-660.0,cm-pad_resize,bg-000000,fo-top:l-text,ie-U3VuLCAxMiBKdWw%3D,fs-29,co-FFFFFF,ly-612,lx-24,pa-8_0_0_0,l-end/et00505151-muvdbvdsrg-portrait.jpg",
    "time": "10:00 AM",
    "duration": "6 Hour",
    "language": "Hindi, Urdu",
    "genre": "Classic"
  },
  {
    "title": "Love You Mom",
    "date": "Sun, 12 Jul",
    "venue": "Akshara Theatre: Delhi",
    "price": "100",
    "genreLine": "Hindi",
    "link": "https://in.bookmyshow.com/plays/love-you-mom/ET00506141",
    "image": "https://assets-in.bmscdn.com/discovery-catalog/events/tr:w-400,h-600,bg-CCCCCC,e-usm-2-2-0.5-0.008:w-400.0,h-660.0,cm-pad_resize,bg-000000,fo-top:l-text,ie-U3VuLCAxMiBKdWw%3D,fs-29,co-FFFFFF,ly-612,lx-24,pa-8_0_0_0,l-end/et00506141-lnyeeptwry-portrait.jpg",
    "time": "5:00 PM",
    "duration": "1 Hour",
    "language": "Hindi",
    "genre": "All age groups"
  },
  {
    "title": "Felicity Theatre Shows",
    "date": "Sun, 12 Jul",
    "venue": "Multiple Venues",
    "price": "499",
    "genreLine": "Hindi",
    "link": "https://in.bookmyshow.com/plays/felicity-theatre-shows/ET00355193",
    "image": "https://assets-in.bmscdn.com/discovery-catalog/events/tr:w-400,h-600,bg-CCCCCC,e-usm-2-2-0.5-0.008:w-400.0,h-660.0,cm-pad_resize,bg-000000,fo-top:l-text,ie-U3VuLCAxMiBKdWw%3D,fs-29,co-FFFFFF,ly-612,lx-24,pa-8_0_0_0,l-end:l-image,i-discovery-catalog@@icons@@bundle-icon-shadow-4x.png,lx-15,ly-15,w-50,l-end/et00355193-ftmptytjvk-portrait.jpg",
    "time": "",
    "duration": "",
    "language": "Hindi",
    "genre": ""
  },
  {
    "title": "Napunsak and Mujhe Is Aag Se Bachao Mere Doston",
    "date": "Sun, 12 Jul",
    "venue": "The Blank Canvas, LTG Auditorium: Delhi",
    "price": "200",
    "genreLine": "Hindi",
    "link": "https://in.bookmyshow.com/plays/napunsak-and-mujhe-is-aag-se-bachao-mere-doston/ET00506291",
    "image": "https://assets-in.bmscdn.com/discovery-catalog/events/tr:w-400,h-600,bg-CCCCCC,e-usm-2-2-0.5-0.008:w-400.0,h-660.0,cm-pad_resize,bg-000000,fo-top:l-text,ie-U3VuLCAxMiBKdWw%3D,fs-29,co-FFFFFF,ly-612,lx-24,pa-8_0_0_0,l-end/et00506291-evzhfalxgv-portrait.jpg",
    "time": "7:15 PM",
    "duration": "1 hour 10 min",
    "language": "Hindi",
    "genre": "Drama"
  },
  {
    "title": "Akaar Live- Phir Se",
    "date": "Sun, 12 Jul",
    "venue": "The Comedy Theatre - Hauz Khass Village: Delhi",
    "price": "299",
    "genreLine": "Hindi/English",
    "link": "https://in.bookmyshow.com/plays/akaar-live-phir-se/ET00505738",
    "image": "https://assets-in.bmscdn.com/discovery-catalog/events/tr:w-400,h-600,bg-CCCCCC,e-usm-2-2-0.5-0.008:w-400.0,h-660.0,cm-pad_resize,bg-000000,fo-top:l-text,ie-U3VuLCAxMiBKdWw%3D,fs-29,co-FFFFFF,ly-612,lx-24,pa-8_0_0_0,l-end/et00505738-gylmxydfcb-portrait.jpg",
    "time": "1:30 PM",
    "duration": "2 Hour",
    "language": "Hindi, English",
    "genre": "Musical"
  },
  {
    "title": "Locked Within",
    "date": "Fri, 17 Jul",
    "venue": "Akshara Theatre: Delhi",
    "price": "250",
    "genreLine": "Hindi",
    "link": "https://in.bookmyshow.com/plays/locked-within/ET00504858",
    "image": "https://assets-in.bmscdn.com/discovery-catalog/events/tr:w-400,h-600,bg-CCCCCC,e-usm-2-2-0.5-0.008:w-400.0,h-660.0,cm-pad_resize,bg-000000,fo-top:l-text,ie-RnJpLCAxNyBKdWw%3D,fs-29,co-FFFFFF,ly-612,lx-24,pa-8_0_0_0,l-end/et00504858-bzrwkfetwm-portrait.jpg",
    "time": "3:00 PM",
    "duration": "1 hour 15 min",
    "language": "Hindi",
    "genre": "Akshara Theatre: Delhi"
  },
  {
    "title": "Rashk",
    "date": "Fri, 17 Jul",
    "venue": "Akshara Theatre: Delhi",
    "price": "250",
    "genreLine": "Hindi",
    "link": "https://in.bookmyshow.com/plays/rashk/ET00495820",
    "image": "https://assets-in.bmscdn.com/discovery-catalog/events/tr:w-400,h-600,bg-CCCCCC,e-usm-2-2-0.5-0.008:w-400.0,h-660.0,cm-pad_resize,bg-000000,fo-top:l-text,ie-RnJpLCAxNyBKdWw%3D,fs-29,co-FFFFFF,ly-612,lx-24,pa-8_0_0_0,l-end/et00495820-zdkktpgcfe-portrait.jpg",
    "time": "6:30 PM",
    "duration": "1 hour 20 min",
    "language": "Hindi",
    "genre": "Adaptation, Adventure, Comedy, Drama, Tragedy"
  },
  {
    "title": "Chuhal",
    "date": "Sat, 18 Jul",
    "venue": "The Blank Canvas, LTG Auditorium: Delhi",
    "price": "299",
    "genreLine": "Hindi",
    "link": "https://in.bookmyshow.com/plays/chuhal/ET00505437",
    "image": "https://assets-in.bmscdn.com/discovery-catalog/events/tr:w-400,h-600,bg-CCCCCC,e-usm-2-2-0.5-0.008:w-400.0,h-660.0,cm-pad_resize,bg-000000,fo-top:l-text,ie-U2F0LCAxOCBKdWw%3D,fs-29,co-FFFFFF,ly-612,lx-24,pa-8_0_0_0,l-end/et00505437-yjvnmwahak-portrait.jpg",
    "time": "7:15 PM",
    "duration": "1 hour 25 min",
    "language": "Hindi",
    "genre": "Drama"
  },
  {
    "title": "Krishna Katha - A Spectacular Broadway",
    "date": "Sat, 18 Jul onwards",
    "venue": "Kamani Auditorium: Delhi",
    "price": "1499",
    "genreLine": "Hindi",
    "link": "https://in.bookmyshow.com/plays/krishna-katha-a-spectacular-broadway/ET00497592",
    "image": "https://assets-in.bmscdn.com/discovery-catalog/events/tr:w-400,h-600,bg-CCCCCC,e-usm-2-2-0.5-0.008:w-400.0,h-660.0,cm-pad_resize,bg-000000,fo-top:l-text,ie-U2F0LCAxOCBKdWwgb253YXJkcw%3D%3D,fs-29,co-FFFFFF,ly-612,lx-24,pa-8_0_0_0,l-end/et00497592-rpnecfvdfy-portrait.jpg",
    "time": "",
    "duration": "2 Hour",
    "language": "Hindi, Marathi",
    "genre": ""
  },
  {
    "title": "Manto- Kamra No 9",
    "date": "Sat, 18 Jul",
    "venue": "Akshara Theatre: Delhi",
    "price": "250",
    "genreLine": "Hindi/Urdu",
    "link": "https://in.bookmyshow.com/plays/manto-kamra-no-9/ET00398706",
    "image": "https://assets-in.bmscdn.com/discovery-catalog/events/tr:w-400,h-600,bg-CCCCCC,e-usm-2-2-0.5-0.008:w-400.0,h-660.0,cm-pad_resize,bg-000000,fo-top:l-text,ie-U2F0LCAxOCBKdWw%3D,fs-29,co-FFFFFF,ly-612,lx-24,pa-8_0_0_0,l-end/et00398706-wqwchkabke-portrait.jpg",
    "time": "3:05 PM",
    "duration": "1 Hour",
    "language": "Hindi, Urdu",
    "genre": "All age groups"
  },
  {
    "title": "Who's Afraid Of Virginia Woolf",
    "date": "Sat, 18 Jul",
    "venue": "The Piano Man: Gurugram",
    "price": "499",
    "genreLine": "English",
    "link": "https://in.bookmyshow.com/plays/who-s-afraid-of-virginia-woolf/ET00459276",
    "image": "https://assets-in.bmscdn.com/discovery-catalog/events/tr:w-400,h-600,bg-CCCCCC,e-usm-2-2-0.5-0.008:w-400.0,h-660.0,cm-pad_resize,bg-000000,fo-top:l-text,ie-U2F0LCAxOCBKdWw%3D,fs-29,co-FFFFFF,ly-612,lx-24,pa-8_0_0_0,l-end/et00459276-hztyxmhnnt-portrait.jpg",
    "time": "4:00 PM",
    "duration": "1 hour 30 min",
    "language": "English",
    "genre": "Comedy, Drama, Thriller"
  },
  {
    "title": "Shivaji Underground in Bheemnagar Mohalla",
    "date": "Sat, 18 Jul onwards",
    "venue": "Hutatma Smruti Mandir: Solapur",
    "price": "300",
    "genreLine": "Marathi",
    "link": "https://in.bookmyshow.com/plays/shivaji-underground-in-bhimnagar-mohalla/ET00455674",
    "image": "https://assets-in.bmscdn.com/discovery-catalog/events/tr:w-400,h-600,bg-CCCCCC,e-usm-2-2-0.5-0.008:w-400.0,h-660.0,cm-pad_resize,bg-000000,fo-top:l-text,ie-U2F0LCAxOCBKdWwgb253YXJkcw%3D%3D,fs-29,co-FFFFFF,ly-612,lx-24,pa-8_0_0_0,l-end/et00455674-fktdqhmrwh-portrait.jpg",
    "time": "7:00 PM",
    "duration": "2 hour",
    "language": "Marathi",
    "genre": "Drama"
  },
  {
    "title": "Shakkar Ke Paanch Daane",
    "date": "Sat, 18 Jul",
    "venue": "The Blank Canvas, LTG Auditorium: Delhi",
    "price": "199",
    "genreLine": "Hindi",
    "link": "https://in.bookmyshow.com/plays/shakkar-ke-paanch-daane/ET00373720",
    "image": "https://assets-in.bmscdn.com/discovery-catalog/events/tr:w-400,h-600,bg-CCCCCC,e-usm-2-2-0.5-0.008:w-400.0,h-660.0,cm-pad_resize,bg-000000,fo-top:l-text,ie-U2F0LCAxOCBKdWw%3D,fs-29,co-FFFFFF,ly-612,lx-24,pa-8_0_0_0,l-end/et00373720-jvkydczthk-portrait.jpg",
    "time": "3:00 PM",
    "duration": "1 hour 25 min",
    "language": "Hindi",
    "genre": "Drama"
  },
  {
    "title": "The Twisted Tales- a trio of comedic drama!",
    "date": "Sat, 18 Jul onwards",
    "venue": "Bangiya Samaj Mancha: Delhi",
    "price": "599",
    "genreLine": "English/Hindi",
    "link": "https://in.bookmyshow.com/plays/the-twisted-tales-a-trio-of-comedic-drama/ET00505937",
    "image": "https://assets-in.bmscdn.com/discovery-catalog/events/tr:w-400,h-600,bg-CCCCCC,e-usm-2-2-0.5-0.008:w-400.0,h-660.0,cm-pad_resize,bg-000000,fo-top:l-text,ie-U2F0LCAxOCBKdWwgb253YXJkcw%3D%3D,fs-29,co-FFFFFF,ly-612,lx-24,pa-8_0_0_0,l-end/et00505937-bxscdjelkl-portrait.jpg",
    "time": "7:00 PM",
    "duration": "1 hour 15 min",
    "language": "English, Hindi",
    "genre": "Adaptation, Comedy, Contemporary, Drama"
  },
  {
    "title": "Theatre Acting & Improv Workshop",
    "date": "Sat, 18 Jul onwards",
    "venue": "Akshara Theatre: Delhi",
    "price": "1199",
    "genreLine": "Hindi/English",
    "link": "https://in.bookmyshow.com/plays/theatre-weekend-workshop/ET00491603",
    "image": "https://assets-in.bmscdn.com/discovery-catalog/events/tr:w-400,h-600,bg-CCCCCC,e-usm-2-2-0.5-0.008:w-400.0,h-660.0,cm-pad_resize,bg-000000,fo-top:l-text,ie-U2F0LCAxOCBKdWwgb253YXJkcw%3D%3D,fs-29,co-FFFFFF,ly-612,lx-24,pa-8_0_0_0,l-end/et00491603-ulmrqtwnnn-portrait.jpg",
    "time": "1:35 PM",
    "duration": "3 Hour",
    "language": "Hindi, English",
    "genre": "Classic, Comedy, Drama"
  },
  {
    "title": "A Bhoot Purv",
    "date": "Sat, 18 Jul",
    "venue": "Little Theatre Group (LTG) Auditorium: Delhi",
    "price": "200",
    "genreLine": "Hindi",
    "link": "https://in.bookmyshow.com/plays/a-bhoot-purv/ET00504466",
    "image": "https://assets-in.bmscdn.com/discovery-catalog/events/tr:w-400,h-600,bg-CCCCCC,e-usm-2-2-0.5-0.008:w-400.0,h-660.0,cm-pad_resize,bg-000000,fo-top:l-text,ie-U2F0LCAxOCBKdWw%3D,fs-29,co-FFFFFF,ly-612,lx-24,pa-8_0_0_0,l-end/et00504466-slmwmquvpd-portrait.jpg",
    "time": "5:00 PM",
    "duration": "1 hour 20 min",
    "language": "Hindi",
    "genre": "All age groups"
  },
  {
    "title": "Bunkar... Stories Woven Anew",
    "date": "Sat, 18 Jul",
    "venue": "The Stein Auditorium, India Habitat Centre: Delhi",
    "price": "200",
    "genreLine": "Hindi",
    "link": "https://in.bookmyshow.com/plays/bunka-stories-woven-anew/ET00503901",
    "image": "https://assets-in.bmscdn.com/discovery-catalog/events/tr:w-400,h-600,bg-CCCCCC,e-usm-2-2-0.5-0.008:w-400.0,h-660.0,cm-pad_resize,bg-000000,fo-top:l-text,ie-U2F0LCAxOCBKdWw%3D,fs-29,co-FFFFFF,ly-612,lx-24,pa-8_0_0_0,l-end/et00503901-guekglfest-portrait.jpg",
    "time": "",
    "duration": "1 hour 15 min",
    "language": "Hindi, Marathi",
    "genre": ""
  },
  {
    "title": "Raat Ke Afsane : Qutub Minar : Heritage Walk",
    "date": "Sat, 18 Jul onwards",
    "venue": "Qutub Minar: Delhi",
    "price": "650",
    "genreLine": "English/Hindi/Hinglish",
    "link": "https://in.bookmyshow.com/plays/raat-ke-afsane-qutub-minar-heritage-walk/ET00455198",
    "image": "https://assets-in.bmscdn.com/discovery-catalog/events/tr:w-400,h-600,bg-CCCCCC,e-usm-2-2-0.5-0.008:w-400.0,h-660.0,cm-pad_resize,bg-000000,fo-top:l-text,ie-U2F0LCAxOCBKdWwgb253YXJkcw%3D%3D,fs-29,co-FFFFFF,ly-612,lx-24,pa-8_0_0_0,l-end/et00455198-qxnnernelc-portrait.jpg",
    "time": "6:30 PM",
    "duration": "1 hour 30 min",
    "language": "English, Hindi, Hinglish",
    "genre": "All age groups"
  },
  {
    "title": "Dastaan-e-Dev Anand",
    "date": "Sat, 18 Jul",
    "venue": "Eternal Oasis: Gurugram",
    "price": "450",
    "genreLine": "Hindi",
    "link": "https://in.bookmyshow.com/plays/dastaan-e-dev-anand/ET00505706",
    "image": "https://assets-in.bmscdn.com/discovery-catalog/events/tr:w-400,h-600,bg-CCCCCC,e-usm-2-2-0.5-0.008:w-400.0,h-660.0,cm-pad_resize,bg-000000,fo-top:l-text,ie-U2F0LCAxOCBKdWw%3D,fs-29,co-FFFFFF,ly-612,lx-24,pa-8_0_0_0,l-end/et00505706-hybgwmeugz-portrait.jpg",
    "time": "5:30 PM",
    "duration": "2 Hour",
    "language": "Hindi",
    "genre": "All age groups"
  },
  {
    "title": "Munshi Premchand 's Kafan",
    "date": "Sat, 18 Jul",
    "venue": "Akshara Theatre: Delhi",
    "price": "300",
    "genreLine": "Hindi",
    "link": "https://in.bookmyshow.com/plays/munshi-premchand-s-kafan/ET00451202",
    "image": "https://assets-in.bmscdn.com/discovery-catalog/events/tr:w-400,h-600,bg-CCCCCC,e-usm-2-2-0.5-0.008:w-400.0,h-660.0,cm-pad_resize,bg-000000,fo-top:l-text,ie-U2F0LCAxOCBKdWw%3D,fs-29,co-FFFFFF,ly-612,lx-24,pa-8_0_0_0,l-end/et00451202-ggjtkbuvxb-portrait.jpg",
    "time": "",
    "duration": "1 hour 15 min",
    "language": "Hindi, Marathi",
    "genre": ""
  },
  {
    "title": "Taj Mahal Ka Tender",
    "date": "Sat, 18 Jul",
    "venue": "Alliance Francaise: Delhi",
    "price": "500",
    "genreLine": "Hindustani",
    "link": "https://in.bookmyshow.com/plays/taj-mahal-ka-tender/ET00361093",
    "image": "https://assets-in.bmscdn.com/discovery-catalog/events/tr:w-400,h-600,bg-CCCCCC,e-usm-2-2-0.5-0.008:w-400.0,h-660.0,cm-pad_resize,bg-000000,fo-top:l-text,ie-U2F0LCAxOCBKdWw%3D,fs-29,co-FFFFFF,ly-612,lx-24,pa-8_0_0_0,l-end/et00361093-ukxdezjatn-portrait.jpg",
    "time": "7:00 PM",
    "duration": "1 hour 45 min",
    "language": "",
    "genre": "Hindustani"
  },
  {
    "title": "Eidgah - Munshi Premchand",
    "date": "Sat, 18 Jul",
    "venue": "Akshara Theatre: Delhi",
    "price": "300",
    "genreLine": "Hindi/Urdu",
    "link": "https://in.bookmyshow.com/plays/eidgah-munshi-premchand/ET00368043",
    "image": "https://assets-in.bmscdn.com/discovery-catalog/events/tr:w-400,h-600,bg-CCCCCC,e-usm-2-2-0.5-0.008:w-400.0,h-660.0,cm-pad_resize,bg-000000,fo-top:l-text,ie-U2F0LCAxOCBKdWw%3D,fs-29,co-FFFFFF,ly-612,lx-24,pa-8_0_0_0,l-end/et00368043-sqrggjhktj-portrait.jpg",
    "time": "5:15 PM",
    "duration": "1 hour 30 min",
    "language": "Hindi, Urdu",
    "genre": "All age groups"
  },
  {
    "title": "Delhi events you cannot miss ft. EIH Heritage Walk",
    "date": "Sat, 18 Jul onwards",
    "venue": "Multiple Venues",
    "price": "650",
    "genreLine": "English/Hindi",
    "link": "https://in.bookmyshow.com/plays/delhi-events-you-cannot-miss-ft-eih-heritage-walk/ET00461179",
    "image": "https://assets-in.bmscdn.com/discovery-catalog/events/tr:w-400,h-600,bg-CCCCCC,e-usm-2-2-0.5-0.008:w-400.0,h-660.0,cm-pad_resize,bg-000000,fo-top:l-text,ie-U2F0LCAxOCBKdWwgb253YXJkcw%3D%3D,fs-29,co-FFFFFF,ly-612,lx-24,pa-8_0_0_0,l-end:l-image,i-discovery-catalog@@icons@@bundle-icon-shadow-4x.png,lx-15,ly-15,w-50,l-end/et00461179-qxvypnhmez-portrait.jpg",
    "time": "",
    "duration": "1 hour 30 min",
    "language": "Hindi, English",
    "genre": ""
  },
  {
    "title": "Zukham Jari Hai",
    "date": "Sun, 19 Jul",
    "venue": "Akshara Theatre: Delhi",
    "price": "300",
    "genreLine": "Hindi",
    "link": "https://in.bookmyshow.com/plays/zukham-jari-hai/ET00358234",
    "image": "https://assets-in.bmscdn.com/discovery-catalog/events/tr:w-400,h-600,bg-CCCCCC,e-usm-2-2-0.5-0.008:w-400.0,h-660.0,cm-pad_resize,bg-000000,fo-top:l-text,ie-U3VuLCAxOSBKdWw%3D,fs-29,co-FFFFFF,ly-612,lx-24,pa-8_0_0_0,l-end/et00358234-cjpxbfxznt-portrait.jpg",
    "time": "5:15 PM",
    "duration": "50 Min",
    "language": "Hindi",
    "genre": "Comedy, Drama"
  },
  {
    "title": "Haunted Walk: Mehrauli Archaeological Park",
    "date": "Sun, 19 Jul",
    "venue": "Mehrauli Archaeological Park: Delhi",
    "price": "650",
    "genreLine": "English/Hindi/Hinglish",
    "link": "https://in.bookmyshow.com/plays/heritage-walk-mehrauli-archaeological-park/ET00435705",
    "image": "https://assets-in.bmscdn.com/discovery-catalog/events/tr:w-400,h-600,bg-CCCCCC,e-usm-2-2-0.5-0.008:w-400.0,h-660.0,cm-pad_resize,bg-000000,fo-top:l-text,ie-U3VuLCAxOSBKdWw%3D,fs-29,co-FFFFFF,ly-612,lx-24,pa-8_0_0_0,l-end/et00435705-hsllkzevqy-portrait.jpg",
    "time": "5:00 PM",
    "duration": "2 Hour",
    "language": "English, Hindi, Hinglish",
    "genre": "All age groups"
  },
  {
    "title": "Charandas Chor",
    "date": "Sun, 19 Jul onwards",
    "venue": "Akshara Theatre: Delhi",
    "price": "150",
    "genreLine": "Hindi",
    "link": "https://in.bookmyshow.com/plays/charandas-chor/ET00379577",
    "image": "https://assets-in.bmscdn.com/discovery-catalog/events/tr:w-400,h-600,bg-CCCCCC,e-usm-2-2-0.5-0.008:w-400.0,h-660.0,cm-pad_resize,bg-000000,fo-top:l-text,ie-U3VuLCAxOSBKdWwgb253YXJkcw%3D%3D,fs-29,co-FFFFFF,ly-612,lx-24,pa-8_0_0_0,l-end/et00379577-vywjvnqhrq-portrait.jpg",
    "time": "7:00 PM",
    "duration": "1 hour 30 min",
    "language": "Hindi",
    "genre": "Comedy"
  },
  {
    "title": "Badass Begum : Old Delhi Heritage Walk",
    "date": "Sun, 19 Jul",
    "venue": "Chandni Chowk Metro Station: Delhi",
    "price": "900",
    "genreLine": "English/Hindi",
    "link": "https://in.bookmyshow.com/plays/badass-begum-old-delhi-heritage-walk/ET00479741",
    "image": "https://assets-in.bmscdn.com/discovery-catalog/events/tr:w-400,h-600,bg-CCCCCC,e-usm-2-2-0.5-0.008:w-400.0,h-660.0,cm-pad_resize,bg-000000,fo-top:l-text,ie-U3VuLCAxOSBKdWw%3D,fs-29,co-FFFFFF,ly-612,lx-24,pa-8_0_0_0,l-end/et00479741-centysfhdf-portrait.jpg",
    "time": "7:30 AM",
    "duration": "2 Hour",
    "language": "English, Hindi",
    "genre": "All age groups"
  },
  {
    "title": "Manish Kumar LIVE : A poetry show",
    "date": "Sun, 19 Jul",
    "venue": "Hideout Studio: Delhi",
    "price": "299",
    "genreLine": "Hindi",
    "link": "https://in.bookmyshow.com/plays/apnapan-rajul-ratna-live/ET00405351",
    "image": "https://assets-in.bmscdn.com/discovery-catalog/events/tr:w-400,h-600,bg-CCCCCC,e-usm-2-2-0.5-0.008:w-400.0,h-660.0,cm-pad_resize,bg-000000,fo-top:l-text,ie-U3VuLCAxOSBKdWw%3D,fs-29,co-FFFFFF,ly-612,lx-24,pa-8_0_0_0,l-end/et00405351-hkywvlbmqw-portrait.jpg",
    "time": "4:01 PM",
    "duration": "1 hour 10 min",
    "language": "Hindi",
    "genre": "Adventure, Biography, Comedy"
  },
  {
    "title": "Immersive Play - Khol Do",
    "date": "Sun, 19 Jul",
    "venue": "Soch Theatre Group: Delhi",
    "price": "150",
    "genreLine": "Hindi/Urdu",
    "link": "https://in.bookmyshow.com/plays/immersive-play-khol-do/ET00503783",
    "image": "https://assets-in.bmscdn.com/discovery-catalog/events/tr:w-400,h-600,bg-CCCCCC,e-usm-2-2-0.5-0.008:w-400.0,h-660.0,cm-pad_resize,bg-000000,fo-top:l-text,ie-U3VuLCAxOSBKdWw%3D,fs-29,co-FFFFFF,ly-612,lx-24,pa-8_0_0_0,l-end/et00503783-engswksfrh-portrait.jpg",
    "time": "5:00 PM",
    "duration": "1 Hour",
    "language": "Hindi, Urdu",
    "genre": "Adaptation, Drama, Historical, Period"
  },
  {
    "title": "Tawaifbaazi : A Tragic Tale",
    "date": "Sun, 19 Jul",
    "venue": "Chawri Bazar Metro Station: Delhi",
    "price": "1450",
    "genreLine": "English/Hindi",
    "link": "https://in.bookmyshow.com/plays/tawaifbaazi-a-tragic-tale/ET00489782",
    "image": "https://assets-in.bmscdn.com/discovery-catalog/events/tr:w-400,h-600,bg-CCCCCC,e-usm-2-2-0.5-0.008:w-400.0,h-660.0,cm-pad_resize,bg-000000,fo-top:l-text,ie-U3VuLCAxOSBKdWw%3D,fs-29,co-FFFFFF,ly-612,lx-24,pa-8_0_0_0,l-end/et00489782-ucquawhhsr-portrait.jpg",
    "time": "9:00 AM",
    "duration": "2 hour",
    "language": "English, Hindi",
    "genre": "Classic, Historical, Tragedy, Tribute"
  },
  {
    "title": "JAANI Live",
    "date": "Sun, 19 Jul",
    "venue": "Hideout Studio: Delhi",
    "price": "399",
    "genreLine": "Hindi",
    "link": "https://in.bookmyshow.com/plays/jaani-live/ET00500771",
    "image": "https://assets-in.bmscdn.com/discovery-catalog/events/tr:w-400,h-600,bg-CCCCCC,e-usm-2-2-0.5-0.008:w-400.0,h-660.0,cm-pad_resize,bg-000000,fo-top:l-text,ie-U3VuLCAxOSBKdWw%3D,fs-29,co-FFFFFF,ly-612,lx-24,pa-8_0_0_0,l-end/et00500771-gsgfcbfpnw-portrait.jpg",
    "time": "6:00 PM",
    "duration": "1 hour 10 min",
    "language": "Hindi",
    "genre": "Classic, Romantic"
  },
  {
    "title": "The Lover - A Play In English",
    "date": "Sun, 19 Jul",
    "venue": "The Piano Man: Gurugram",
    "price": "499",
    "genreLine": "English",
    "link": "https://in.bookmyshow.com/plays/the-lover-a-play-in-english/ET00505805",
    "image": "https://assets-in.bmscdn.com/discovery-catalog/events/tr:w-400,h-600,bg-CCCCCC,e-usm-2-2-0.5-0.008:w-400.0,h-660.0,cm-pad_resize,bg-000000,fo-top:l-text,ie-U3VuLCAxOSBKdWw%3D,fs-29,co-FFFFFF,ly-612,lx-24,pa-8_0_0_0,l-end/et00505805-jmgqtnxahy-portrait.jpg",
    "time": "4:00 PM",
    "duration": "1 hour 15 min",
    "language": "English",
    "genre": "Drama, Musical, Psychological"
  },
  {
    "title": "Sakharam Binder",
    "date": "Sun, 19 Jul",
    "venue": "Alliance Francaise: Delhi",
    "price": "300",
    "genreLine": "Hindustani",
    "link": "https://in.bookmyshow.com/plays/sakharam-binder/ET00499570",
    "image": "https://assets-in.bmscdn.com/discovery-catalog/events/tr:w-400,h-600,bg-CCCCCC,e-usm-2-2-0.5-0.008:w-400.0,h-660.0,cm-pad_resize,bg-000000,fo-top:l-text,ie-U3VuLCAxOSBKdWw%3D,fs-29,co-FFFFFF,ly-612,lx-24,pa-8_0_0_0,l-end/et00499570-dnyumljtwg-portrait.jpg",
    "time": "7:30 PM",
    "duration": "1 hour 30 min",
    "language": "Marathi",
    "genre": "Hindustani"
  },
  {
    "title": "Khilji Ka Daant",
    "date": "Sun, 19 Jul",
    "venue": "Akshara Theatre: Delhi",
    "price": "300",
    "genreLine": "Hindi",
    "link": "https://in.bookmyshow.com/plays/khilji-ka-daant/ET00358238",
    "image": "https://assets-in.bmscdn.com/discovery-catalog/events/tr:w-400,h-600,bg-CCCCCC,e-usm-2-2-0.5-0.008:w-400.0,h-660.0,cm-pad_resize,bg-000000,fo-top:l-text,ie-U3VuLCAxOSBKdWw%3D,fs-29,co-FFFFFF,ly-612,lx-24,pa-8_0_0_0,l-end/et00358238-vztfkvqvyd-portrait.jpg",
    "time": "4:00 PM",
    "duration": "40 Min",
    "language": "Hindi",
    "genre": "Drama"
  },
  {
    "title": "Aavran Theatre Group",
    "date": "Sun, 19 Jul",
    "venue": "Multiple Venues",
    "price": "300",
    "genreLine": "Hindi",
    "link": "https://in.bookmyshow.com/plays/aavran-theatre-group/ET00356121",
    "image": "https://assets-in.bmscdn.com/discovery-catalog/events/tr:w-400,h-600,bg-CCCCCC,e-usm-2-2-0.5-0.008:w-400.0,h-660.0,cm-pad_resize,bg-000000,fo-top:l-text,ie-U3VuLCAxOSBKdWw%3D,fs-29,co-FFFFFF,ly-612,lx-24,pa-8_0_0_0,l-end:l-image,i-discovery-catalog@@icons@@bundle-icon-shadow-4x.png,lx-15,ly-15,w-50,l-end/et00356121-ftkwwgjrjl-portrait.jpg",
    "time": "",
    "duration": "1 hour 50 min",
    "language": "Hindi",
    "genre": ""
  },
  {
    "title": "Hamlet",
    "date": "Sun, 19 Jul",
    "venue": "Little Theatre Group (LTG) Auditorium: Delhi",
    "price": "200",
    "genreLine": "Hindi",
    "link": "https://in.bookmyshow.com/plays/hamlet/ET00506423",
    "image": "https://assets-in.bmscdn.com/discovery-catalog/events/tr:w-400,h-600,bg-CCCCCC,e-usm-2-2-0.5-0.008:w-400.0,h-660.0,cm-pad_resize,bg-000000,fo-top:l-text,ie-U3VuLCAxOSBKdWw%3D,fs-29,co-FFFFFF,ly-612,lx-24,pa-8_0_0_0,l-end/et00506423-avzttewydd-portrait.jpg",
    "time": "7:00 PM",
    "duration": "1 hour 45 min",
    "language": "Hindi",
    "genre": "Psychological"
  },
  {
    "title": "Rishton Ka Satyagrah",
    "date": "Sun, 19 Jul",
    "venue": "The Blank Canvas, LTG Auditorium: Delhi",
    "price": "150",
    "genreLine": "Hindi/English",
    "link": "https://in.bookmyshow.com/plays/rishton-ka-satyagrah/ET00506137",
    "image": "https://assets-in.bmscdn.com/discovery-catalog/events/tr:w-400,h-600,bg-CCCCCC,e-usm-2-2-0.5-0.008:w-400.0,h-660.0,cm-pad_resize,bg-000000,fo-top:l-text,ie-U3VuLCAxOSBKdWw%3D,fs-29,co-FFFFFF,ly-612,lx-24,pa-8_0_0_0,l-end/et00506137-pjdcmpwlea-portrait.jpg",
    "time": "6:00 PM",
    "duration": "1 hour 15 min",
    "language": "Hindi, English",
    "genre": "All age groups"
  },
  {
    "title": "FAISLA ABHI BAKI HAI",
    "date": "Fri, 24 Jul",
    "venue": "Akshara Theatre: Delhi",
    "price": "499",
    "genreLine": "Hindi",
    "link": "https://in.bookmyshow.com/plays/faisla-abhi-baki-hai/ET00506370",
    "image": "https://assets-in.bmscdn.com/discovery-catalog/events/tr:w-400,h-600,bg-CCCCCC,e-usm-2-2-0.5-0.008:w-400.0,h-660.0,cm-pad_resize,bg-000000,fo-top:l-text,ie-RnJpLCAyNCBKdWw%3D,fs-29,co-FFFFFF,ly-612,lx-24,pa-8_0_0_0,l-end/et00506370-yermlguplx-portrait.jpg",
    "time": "",
    "duration": "1 hour 15 min",
    "language": "Hindi, Marathi",
    "genre": ""
  },
  {
    "title": "STORIES OF ANTON CHEKHOV",
    "date": "Sat, 25 Jul",
    "venue": "The Blank Canvas, LTG Auditorium: Delhi",
    "price": "300",
    "genreLine": "Hindi",
    "link": "https://in.bookmyshow.com/plays/stories-of-anton-chekhov/ET00500356",
    "image": "https://assets-in.bmscdn.com/discovery-catalog/events/tr:w-400,h-600,bg-CCCCCC,e-usm-2-2-0.5-0.008:w-400.0,h-660.0,cm-pad_resize,bg-000000,fo-top:l-text,ie-U2F0LCAyNSBKdWw%3D,fs-29,co-FFFFFF,ly-612,lx-24,pa-8_0_0_0,l-end/et00500356-edxjvbykmd-portrait.jpg",
    "time": "",
    "duration": "1 Hour",
    "language": "Hindi",
    "genre": ""
  },
  {
    "title": "Kali Shalwar by Manto",
    "date": "Sat, 25 Jul",
    "venue": "Shri Ram Centre for Performing Arts: Delhi",
    "price": "199",
    "genreLine": "Hindi",
    "link": "https://in.bookmyshow.com/plays/kali-shalwar-by-manto/ET00445566",
    "image": "https://assets-in.bmscdn.com/discovery-catalog/events/tr:w-400,h-600,bg-CCCCCC,e-usm-2-2-0.5-0.008:w-400.0,h-660.0,cm-pad_resize,bg-000000,fo-top:l-text,ie-U2F0LCAyNSBKdWw%3D,fs-29,co-FFFFFF,ly-612,lx-24,pa-8_0_0_0,l-end/et00445566-wexclezbvm-portrait.jpg",
    "time": "",
    "duration": "1 hour 30 min",
    "language": "Hindi, Marathi",
    "genre": ""
  },
  {
    "title": "Abhi na Jao Chhod kar by Jasmine Babbar",
    "date": "Sat, 25 Jul",
    "venue": "Bipin Chandra Pal Bhavan Auditorium: Delhi",
    "price": "699",
    "genreLine": "Hindustani/Punjabi/English",
    "link": "https://in.bookmyshow.com/plays/jasmine-babbar-live/ET00489283",
    "image": "https://assets-in.bmscdn.com/discovery-catalog/events/tr:w-400,h-600,bg-CCCCCC,e-usm-2-2-0.5-0.008:w-400.0,h-660.0,cm-pad_resize,bg-000000,fo-top:l-text,ie-U2F0LCAyNSBKdWw%3D,fs-29,co-FFFFFF,ly-612,lx-24,pa-8_0_0_0,l-end/et00489283-qdduahyqpt-portrait.jpg",
    "time": "6:30 PM",
    "duration": "1 hour 30 min",
    "language": "Hindustani, Punjabi, English",
    "genre": "Drama, Musical, Romantic"
  },
  {
    "title": "NTLive Broadcast The Playboy of the Western World",
    "date": "Sun, 26 Jul",
    "venue": "The Stein Auditorium, India Habitat Centre: Delhi",
    "price": "250",
    "genreLine": "English",
    "link": "https://in.bookmyshow.com/plays/ntlive-broadcast-the-playboy-of-the-western-world/ET00503904",
    "image": "https://assets-in.bmscdn.com/discovery-catalog/events/tr:w-400,h-600,bg-CCCCCC,e-usm-2-2-0.5-0.008:w-400.0,h-660.0,cm-pad_resize,bg-000000,fo-top:l-text,ie-U3VuLCAyNiBKdWw%3D,fs-29,co-FFFFFF,ly-612,lx-24,pa-8_0_0_0,l-end/et00503904-bvmfhvnucy-portrait.jpg",
    "time": "7:00 PM",
    "duration": "2 hour",
    "language": "English",
    "genre": "Drama"
  },
  {
    "title": "EQUUS - DELHI",
    "date": "Sun, 26 Jul",
    "venue": "Little Theatre Group (LTG) Auditorium: Delhi",
    "price": "300",
    "genreLine": "English",
    "link": "https://in.bookmyshow.com/plays/equus-delhi/ET00501889",
    "image": "https://assets-in.bmscdn.com/discovery-catalog/events/tr:w-400,h-600,bg-CCCCCC,e-usm-2-2-0.5-0.008:w-400.0,h-660.0,cm-pad_resize,bg-000000,fo-top:l-text,ie-U3VuLCAyNiBKdWw%3D,fs-29,co-FFFFFF,ly-612,lx-24,pa-8_0_0_0,l-end/et00501889-awmblmymfs-portrait.jpg",
    "time": "",
    "duration": "2 Hour",
    "language": "English, Marathi",
    "genre": ""
  },
  {
    "title": "Oedipus by Sophocles",
    "date": "Sun, 26 Jul",
    "venue": "Akshara Theatre: Delhi",
    "price": "200",
    "genreLine": "Hindi",
    "link": "https://in.bookmyshow.com/plays/oedipus-by-sophocles/ET00387966",
    "image": "https://assets-in.bmscdn.com/discovery-catalog/events/tr:w-400,h-600,bg-CCCCCC,e-usm-2-2-0.5-0.008:w-400.0,h-660.0,cm-pad_resize,bg-000000,fo-top:l-text,ie-U3VuLCAyNiBKdWw%3D,fs-29,co-FFFFFF,ly-612,lx-24,pa-8_0_0_0,l-end/et00387966-agnquaynxy-portrait.jpg",
    "time": "3:30 PM",
    "duration": "1 hour 30 min",
    "language": "Hindi",
    "genre": "Drama"
  },
  {
    "title": "Rishton Ka Network",
    "date": "Sun, 26 Jul",
    "venue": "The Piano Man: Gurugram",
    "price": "799",
    "genreLine": "English/Hindi",
    "link": "https://in.bookmyshow.com/plays/rishton-ka-network/ET00504099",
    "image": "https://assets-in.bmscdn.com/discovery-catalog/events/tr:w-400,h-600,bg-CCCCCC,e-usm-2-2-0.5-0.008:w-400.0,h-660.0,cm-pad_resize,bg-000000,fo-top:l-text,ie-U3VuLCAyNiBKdWw%3D,fs-29,co-FFFFFF,ly-612,lx-24,pa-8_0_0_0,l-end/et00504099-xzynnkdwfm-portrait.jpg",
    "time": "5:00 PM",
    "duration": "1 hour 30 min",
    "language": "English, Hindi",
    "genre": "All age groups"
  },
  {
    "title": "Raat Ke Afsane : Safdarjung Tomb",
    "date": "Sun, 26 Jul",
    "venue": "Safdarjung Tomb: Delhi",
    "price": "650",
    "genreLine": "English/Hindi/Hinglish",
    "link": "https://in.bookmyshow.com/plays/heritage-walk-safdarjung-tomb-raat-ke-afsane/ET00497562",
    "image": "https://assets-in.bmscdn.com/discovery-catalog/events/tr:w-400,h-600,bg-CCCCCC,e-usm-2-2-0.5-0.008:w-400.0,h-660.0,cm-pad_resize,bg-000000,fo-top:l-text,ie-U3VuLCAyNiBKdWw%3D,fs-29,co-FFFFFF,ly-612,lx-24,pa-8_0_0_0,l-end/et00497562-ttevffcfpu-portrait.jpg",
    "time": "5:30 PM",
    "duration": "1 hour 30 min",
    "language": "English, Hindi, Hinglish",
    "genre": "All age groups"
  },
  {
    "title": "Bazar-i-Husn :  exploring Tawaif culture",
    "date": "Sun, 26 Jul",
    "venue": "Bazar-i-Husn : exploring Tawaif culture",
    "price": "650",
    "genreLine": "Chawri Bazar Metro Station: Delhi",
    "link": "https://in.bookmyshow.com/plays/tawaifs-and-kothas-exploring-chawri-bazaar/ET00455193",
    "image": "https://assets-in.bmscdn.com/discovery-catalog/events/tr:w-400,h-600,bg-CCCCCC,e-usm-2-2-0.5-0.008:w-400.0,h-660.0,cm-pad_resize,bg-000000,fo-top:l-text,ie-U3VuLCAyNiBKdWw%3D,fs-29,co-FFFFFF,ly-612,lx-24,pa-8_0_0_0,l-end/et00455193-ztdjupdvez-portrait.jpg",
    "time": "7:30 AM",
    "duration": "2 Hour",
    "language": "English, Hindi",
    "genre": "All age groups"
  },
  {
    "title": "Agatha Christie's The Mousetrap",
    "date": "Sun, 26 Jul",
    "venue": "Lok Kala Manch: New Delhi",
    "price": "249",
    "genreLine": "Hindi",
    "link": "https://in.bookmyshow.com/plays/agathe-christie-s-the-mousetrap/ET00502155",
    "image": "https://assets-in.bmscdn.com/discovery-catalog/events/tr:w-400,h-600,bg-CCCCCC,e-usm-2-2-0.5-0.008:w-400.0,h-660.0,cm-pad_resize,bg-000000,fo-top:l-text,ie-U3VuLCAyNiBKdWw%3D,fs-29,co-FFFFFF,ly-612,lx-24,pa-8_0_0_0,l-end/et00502155-hdnnekxcjk-portrait.jpg",
    "time": "",
    "duration": "1 hour 40 min",
    "language": "Hindi, Gujarati",
    "genre": ""
  },
  {
    "title": "Waiting For Godot",
    "date": "Sun, 26 Jul",
    "venue": "Akshara Theatre: Delhi",
    "price": "250",
    "genreLine": "Hindi",
    "link": "https://in.bookmyshow.com/plays/waiting-for-godot/ET00404310",
    "image": "https://assets-in.bmscdn.com/discovery-catalog/events/tr:w-400,h-600,bg-CCCCCC,e-usm-2-2-0.5-0.008:w-400.0,h-660.0,cm-pad_resize,bg-000000,fo-top:l-text,ie-U3VuLCAyNiBKdWw%3D,fs-29,co-FFFFFF,ly-612,lx-24,pa-8_0_0_0,l-end/et00404310-rumrwqxhrv-portrait.jpg",
    "time": "7:31 PM",
    "duration": "1 hour 40 min",
    "language": "Hindi",
    "genre": "Drama"
  },
  {
    "title": "Bimar",
    "date": "Sun, 26 Jul",
    "venue": "Akshara Theatre: Delhi",
    "price": "200",
    "genreLine": "Hindi",
    "link": "https://in.bookmyshow.com/plays/bimar/ET00503768",
    "image": "https://assets-in.bmscdn.com/discovery-catalog/events/tr:w-400,h-600,bg-CCCCCC,e-usm-2-2-0.5-0.008:w-400.0,h-660.0,cm-pad_resize,bg-000000,fo-top:l-text,ie-U3VuLCAyNiBKdWw%3D,fs-29,co-FFFFFF,ly-612,lx-24,pa-8_0_0_0,l-end/et00503768-ayqbgmckdz-portrait.jpg",
    "time": "2:15 PM",
    "duration": "40 Min",
    "language": "Hindi",
    "genre": "Comedy"
  },
  {
    "title": "Twelve Angry Women",
    "date": "Sun, 26 Jul",
    "venue": "Akshara Theatre: Delhi",
    "price": "250",
    "genreLine": "",
    "link": "https://in.bookmyshow.com/plays/twelve-angry-women/ET00497545",
    "image": "https://assets-in.bmscdn.com/discovery-catalog/events/tr:w-400,h-600,bg-CCCCCC,e-usm-2-2-0.5-0.008:w-400.0,h-660.0,cm-pad_resize,bg-000000,fo-top:l-text,ie-U3VuLCAyNiBKdWw%3D,fs-29,co-FFFFFF,ly-612,lx-24,pa-8_0_0_0,l-end/et00497545-xenzezzacg-portrait.jpg",
    "time": "5:30 PM",
    "duration": "1 hour 30 min",
    "language": "Marathi",
    "genre": "Drama"
  },
  {
    "title": "Unmask Theatre Festival",
    "date": "Sun, 26 Jul onwards",
    "venue": "Multiple Venues",
    "price": "200",
    "genreLine": "Hindi",
    "link": "https://in.bookmyshow.com/plays/unmask-winter-theatre-festival/ET00383604",
    "image": "https://assets-in.bmscdn.com/discovery-catalog/events/tr:w-400,h-600,bg-CCCCCC,e-usm-2-2-0.5-0.008:w-400.0,h-660.0,cm-pad_resize,bg-000000,fo-top:l-text,ie-U3VuLCAyNiBKdWwgb253YXJkcw%3D%3D,fs-29,co-FFFFFF,ly-612,lx-24,pa-8_0_0_0,l-end:l-image,i-discovery-catalog@@icons@@bundle-icon-shadow-4x.png,lx-15,ly-15,w-50,l-end/et00383604-llkyxwftdv-portrait.jpg",
    "time": "",
    "duration": "",
    "language": "Hindi",
    "genre": ""
  },
  {
    "title": "Sapno Mein Sahi",
    "date": "Fri, 31 Jul",
    "venue": "Akshara Theatre: Delhi",
    "price": "450",
    "genreLine": "English/Hindi/Urdu",
    "link": "https://in.bookmyshow.com/plays/sapno-mein-sahi/ET00147069",
    "image": "https://assets-in.bmscdn.com/discovery-catalog/events/tr:w-400,h-600,bg-CCCCCC,e-usm-2-2-0.5-0.008:w-400.0,h-660.0,cm-pad_resize,bg-000000,fo-top:l-text,ie-RnJpLCAzMSBKdWw%3D,fs-29,co-FFFFFF,ly-612,lx-24,pa-8_0_0_0,l-end/et00147069-swwxyfmnla-portrait.jpg",
    "time": "",
    "duration": "2 Hour",
    "language": "Hindi, English",
    "genre": ""
  },
  {
    "title": "Devdas - A Grand Musical Stage Spectacle",
    "date": "Sat, 1 Aug",
    "venue": "Apparel House: Gurgaon",
    "price": "1180",
    "genreLine": "Hindi",
    "link": "https://in.bookmyshow.com/plays/devdas-a-grand-musical-stage-spectacle/ET00505801",
    "image": "https://assets-in.bmscdn.com/discovery-catalog/events/tr:w-400,h-600,bg-CCCCCC,e-usm-2-2-0.5-0.008:w-400.0,h-660.0,cm-pad_resize,bg-000000,fo-top:l-text,ie-U2F0LCAxIEF1Zw%3D%3D,fs-29,co-FFFFFF,ly-612,lx-24,pa-8_0_0_0,l-end/et00505801-tdnwugedhj-portrait.jpg",
    "time": "",
    "duration": "2 hour",
    "language": "Hindi, Marathi",
    "genre": ""
  },
  {
    "title": "Jis Lahore Nai Dekhya O Jamyai Nai",
    "date": "Sat, 1 Aug",
    "venue": "Shri Ram Centre for Performing Arts: Delhi",
    "price": "300",
    "genreLine": "Hindustani",
    "link": "https://in.bookmyshow.com/plays/jis-lahore-nai-dekhya-o-jamyai-nai/ET00502325",
    "image": "https://assets-in.bmscdn.com/discovery-catalog/events/tr:w-400,h-600,bg-CCCCCC,e-usm-2-2-0.5-0.008:w-400.0,h-660.0,cm-pad_resize,bg-000000,fo-top:l-text,ie-U2F0LCAxIEF1Zw%3D%3D,fs-29,co-FFFFFF,ly-612,lx-24,pa-8_0_0_0,l-end/et00502325-vgpgwnjeql-portrait.jpg",
    "time": "7:15 PM",
    "duration": "2 Hour",
    "language": "Marathi",
    "genre": "Hindustani"
  },
  {
    "title": "The Big Fat City",
    "date": "Sat, 1 Aug",
    "venue": "The Stein Auditorium, India Habitat Centre: Delhi",
    "price": "200",
    "genreLine": "Hindi",
    "link": "https://in.bookmyshow.com/plays/the-big-fat-city/ET00506356",
    "image": "https://assets-in.bmscdn.com/discovery-catalog/events/tr:w-400,h-600,bg-CCCCCC,e-usm-2-2-0.5-0.008:w-400.0,h-660.0,cm-pad_resize,bg-000000,fo-top:l-text,ie-U2F0LCAxIEF1Zw%3D%3D,fs-29,co-FFFFFF,ly-612,lx-24,pa-8_0_0_0,l-end/et00506356-lexjfyqefl-portrait.jpg",
    "time": "7:30 PM",
    "duration": "1 hour 30 min",
    "language": "Hindi",
    "genre": "Comedy, Drama"
  },
  {
    "title": "Park",
    "date": "Sun, 2 Aug",
    "venue": "Alliance Francaise: Delhi",
    "price": "299",
    "genreLine": "Hindi",
    "link": "https://in.bookmyshow.com/plays/park/ET00337179",
    "image": "https://assets-in.bmscdn.com/discovery-catalog/events/tr:w-400,h-600,bg-CCCCCC,e-usm-2-2-0.5-0.008:w-400.0,h-660.0,cm-pad_resize,bg-000000,fo-top:l-text,ie-U3VuLCAyIEF1Zw%3D%3D,fs-29,co-FFFFFF,ly-612,lx-24,pa-8_0_0_0,l-end/et00337179-zyzxgpldlu-portrait.jpg",
    "time": "7:45 PM",
    "duration": "45 Min",
    "language": "Hindi",
    "genre": "Drama"
  },
  {
    "title": "Varun Sharma Prakash and Sons Fun Unltd.",
    "date": "Sun, 2 Aug",
    "venue": "Alliance Francaise: Delhi",
    "price": "299",
    "genreLine": "Hindi",
    "link": "https://in.bookmyshow.com/plays/varun-sharmas-prakash-and-sons-fun-unltd/ET00368163",
    "image": "https://assets-in.bmscdn.com/discovery-catalog/events/tr:w-400,h-600,bg-CCCCCC,e-usm-2-2-0.5-0.008:w-400.0,h-660.0,cm-pad_resize,bg-000000,fo-top:l-text,ie-U3VuLCAyIEF1Zw%3D%3D,fs-29,co-FFFFFF,ly-612,lx-24,pa-8_0_0_0,l-end/et00368163-cwdpedatgr-portrait.jpg",
    "time": "5:45 PM",
    "duration": "1 hour 15 min",
    "language": "Hindi",
    "genre": "Comedy, Drama"
  },
  {
    "title": "IBNEBATUTI",
    "date": "Sun, 2 Aug",
    "venue": "Shri Ram Centre for Performing Arts: Delhi",
    "price": "150",
    "genreLine": "Hindustani",
    "link": "https://in.bookmyshow.com/plays/ibnebatuti/ET00503647",
    "image": "https://assets-in.bmscdn.com/discovery-catalog/events/tr:w-400,h-600,bg-CCCCCC,e-usm-2-2-0.5-0.008:w-400.0,h-660.0,cm-pad_resize,bg-000000,fo-top:l-text,ie-U3VuLCAyIEF1Zw%3D%3D,fs-29,co-FFFFFF,ly-612,lx-24,pa-8_0_0_0,l-end/et00503647-xryentzntb-portrait.jpg",
    "time": "7:00 PM",
    "duration": "1 hour 45 min",
    "language": "Marathi",
    "genre": "Hindustani"
  },
  {
    "title": "Abhigyan Shakuntalam",
    "date": "Sun, 2 Aug",
    "venue": "M.L. Bhartia Auditorium: Delhi",
    "price": "299",
    "genreLine": "Hindi",
    "link": "https://in.bookmyshow.com/plays/abhigyan-shakuntalam/ET00505926",
    "image": "https://assets-in.bmscdn.com/discovery-catalog/events/tr:w-400,h-600,bg-CCCCCC,e-usm-2-2-0.5-0.008:w-400.0,h-660.0,cm-pad_resize,bg-000000,fo-top:l-text,ie-U3VuLCAyIEF1Zw%3D%3D,fs-29,co-FFFFFF,ly-612,lx-24,pa-8_0_0_0,l-end/et00505926-qqmfnbkxlg-portrait.jpg",
    "time": "4:00 PM",
    "duration": "1 hour 15 min",
    "language": "Hindi",
    "genre": "Drama, Romantic"
  },
  {
    "title": "Jugaad",
    "date": "Sun, 2 Aug",
    "venue": "Shri Ram Centre for Performing Arts: Delhi",
    "price": "100",
    "genreLine": "Hindi",
    "link": "https://in.bookmyshow.com/plays/jugaad/ET00505219",
    "image": "https://assets-in.bmscdn.com/discovery-catalog/events/tr:w-400,h-600,bg-CCCCCC,e-usm-2-2-0.5-0.008:w-400.0,h-660.0,cm-pad_resize,bg-000000,fo-top:l-text,ie-U3VuLCAyIEF1Zw%3D%3D,fs-29,co-FFFFFF,ly-612,lx-24,pa-8_0_0_0,l-end/et00505219-jcwpsyabtu-portrait.jpg",
    "time": "4:00 PM",
    "duration": "1 hour 50 min",
    "language": "Hindi",
    "genre": "Drama"
  },
  {
    "title": "Ardh Kavya",
    "date": "Sun, 2 Aug",
    "venue": "Akshara Theatre: Delhi",
    "price": "500",
    "genreLine": "Hindustani",
    "link": "https://in.bookmyshow.com/plays/ardh-kavya/ET00504259",
    "image": "https://assets-in.bmscdn.com/discovery-catalog/events/tr:w-400,h-600,bg-CCCCCC,e-usm-2-2-0.5-0.008:w-400.0,h-660.0,cm-pad_resize,bg-000000,fo-top:l-text,ie-U3VuLCAyIEF1Zw%3D%3D,fs-29,co-FFFFFF,ly-612,lx-24,pa-8_0_0_0,l-end/et00504259-gjtqtxxmaf-portrait.jpg",
    "time": "4:00 PM",
    "duration": "1 Hour",
    "language": "Hindi, Marathi",
    "genre": "Hindustani"
  },
  {
    "title": "Theatreleela Acting Studio",
    "date": "Sun, 2 Aug",
    "venue": "Multiple Venues",
    "price": "299",
    "genreLine": "Hindi",
    "link": "https://in.bookmyshow.com/plays/theatreleela-acting-studio/ET00378377",
    "image": "https://assets-in.bmscdn.com/discovery-catalog/events/tr:w-400,h-600,bg-CCCCCC,e-usm-2-2-0.5-0.008:w-400.0,h-660.0,cm-pad_resize,bg-000000,fo-top:l-text,ie-U3VuLCAyIEF1Zw%3D%3D,fs-29,co-FFFFFF,ly-612,lx-24,pa-8_0_0_0,l-end:l-image,i-discovery-catalog@@icons@@bundle-icon-shadow-4x.png,lx-15,ly-15,w-50,l-end/et00378377-tupmgeqqkx-portrait.jpg",
    "time": "",
    "duration": "",
    "language": "Hindi",
    "genre": ""
  },
  {
    "title": "Agni Aur Barkha",
    "date": "Sun, 2 Aug",
    "venue": "M.L. Bhartia Auditorium: Delhi",
    "price": "299",
    "genreLine": "Hindi",
    "link": "https://in.bookmyshow.com/plays/agni-aur-barkha/ET00505921",
    "image": "https://assets-in.bmscdn.com/discovery-catalog/events/tr:w-400,h-600,bg-CCCCCC,e-usm-2-2-0.5-0.008:w-400.0,h-660.0,cm-pad_resize,bg-000000,fo-top:l-text,ie-U3VuLCAyIEF1Zw%3D%3D,fs-29,co-FFFFFF,ly-612,lx-24,pa-8_0_0_0,l-end/et00505921-qvkqkfdvez-portrait.jpg",
    "time": "2:30 PM",
    "duration": "1 Hour",
    "language": "Hindi",
    "genre": "Mythological"
  },
  {
    "title": "Ashad Ka Ek Din",
    "date": "Fri, 7 Aug",
    "venue": "Shri Ram Centre for Performing Arts: Delhi",
    "price": "200",
    "genreLine": "Hindi",
    "link": "https://in.bookmyshow.com/plays/ashad-ka-ek-din/ET00328594",
    "image": "https://assets-in.bmscdn.com/discovery-catalog/events/tr:w-400,h-600,bg-CCCCCC,e-usm-2-2-0.5-0.008:w-400.0,h-660.0,cm-pad_resize,bg-000000,fo-top:l-text,ie-RnJpLCA3IEF1Zw%3D%3D,fs-29,co-FFFFFF,ly-612,lx-24,pa-8_0_0_0,l-end/et00328594-mbhxbdbwzm-portrait.jpg",
    "time": "7:00 PM",
    "duration": "1 hour 40 min",
    "language": "Hindi",
    "genre": "All age groups"
  },
  {
    "title": "Don't Dress For Dinner",
    "date": "Sat, 8 Aug onwards",
    "venue": "Little Theatre Group (LTG) Auditorium: Delhi",
    "price": "899",
    "genreLine": "English",
    "link": "https://in.bookmyshow.com/plays/don-t-dress-for-dinner/ET00504792",
    "image": "https://assets-in.bmscdn.com/discovery-catalog/events/tr:w-400,h-600,bg-CCCCCC,e-usm-2-2-0.5-0.008:w-400.0,h-660.0,cm-pad_resize,bg-000000,fo-top:l-text,ie-U2F0LCA4IEF1ZyBvbndhcmRz,fs-29,co-FFFFFF,ly-612,lx-24,pa-8_0_0_0,l-end/et00504792-jntjagscyw-portrait.jpg",
    "time": "7:00 PM",
    "duration": "2 Hour",
    "language": "English",
    "genre": "Comedy, Drama"
  },
  {
    "title": "12 Angry Jurors",
    "date": "Sat, 8 Aug",
    "venue": "Akshara Theatre: Delhi",
    "price": "350",
    "genreLine": "Hindi/English",
    "link": "https://in.bookmyshow.com/plays/12-angry-jurors/ET00502000",
    "image": "https://assets-in.bmscdn.com/discovery-catalog/events/tr:w-400,h-600,bg-CCCCCC,e-usm-2-2-0.5-0.008:w-400.0,h-660.0,cm-pad_resize,bg-000000,fo-top:l-text,ie-U2F0LCA4IEF1Zw%3D%3D,fs-29,co-FFFFFF,ly-612,lx-24,pa-8_0_0_0,l-end/et00502000-jahtdgqzpl-portrait.jpg",
    "time": "6:30 PM",
    "duration": "2 Hour",
    "language": "Hindi, English",
    "genre": "Classic, Drama, Political, Suspense"
  },
  {
    "title": "Rabindranath Tagore's Chokher Bali",
    "date": "Sun, 9 Aug",
    "venue": "Shri Ram Centre for Performing Arts: Delhi",
    "price": "200",
    "genreLine": "Hindi/English",
    "link": "https://in.bookmyshow.com/plays/rabindranath-tagore-s-chokher-bali/ET00439287",
    "image": "https://assets-in.bmscdn.com/discovery-catalog/events/tr:w-400,h-600,bg-CCCCCC,e-usm-2-2-0.5-0.008:w-400.0,h-660.0,cm-pad_resize,bg-000000,fo-top:l-text,ie-U3VuLCA5IEF1Zw%3D%3D,fs-29,co-FFFFFF,ly-612,lx-24,pa-8_0_0_0,l-end/et00439287-qamwszwffh-portrait.jpg",
    "time": "7:00 PM",
    "duration": "2 Hour",
    "language": "Hindi, English",
    "genre": "Drama"
  },
  {
    "title": "Manav Kaul - Prem Kabootar",
    "date": "Sun, 9 Aug",
    "venue": "Shri Ram Centre for Performing Arts: Delhi",
    "price": "200",
    "genreLine": "Hindi",
    "link": "https://in.bookmyshow.com/plays/manav-kaul-prem-kabootar/ET00482151",
    "image": "https://assets-in.bmscdn.com/discovery-catalog/events/tr:w-400,h-600,bg-CCCCCC,e-usm-2-2-0.5-0.008:w-400.0,h-660.0,cm-pad_resize,bg-000000,fo-top:l-text,ie-U3VuLCA5IEF1Zw%3D%3D,fs-29,co-FFFFFF,ly-612,lx-24,pa-8_0_0_0,l-end/et00482151-auxatlbmrs-portrait.jpg",
    "time": "4:30 PM",
    "duration": "1 hour 30 min",
    "language": "Hindi",
    "genre": "All age groups"
  },
  {
    "title": "HUMARE RAM Ft Ashutosh Rana and Rahull R Bhuchar",
    "date": "Fri, 14 Aug onwards",
    "venue": "Kamani Auditorium: Delhi",
    "price": "2299",
    "genreLine": "Hindi",
    "link": "https://in.bookmyshow.com/plays/humare-ram-ft-ashutosh-rana-and-rahull-r-bhuchar/ET00376688",
    "image": "https://assets-in.bmscdn.com/discovery-catalog/events/tr:w-400,h-600,bg-CCCCCC,e-usm-2-2-0.5-0.008:w-400.0,h-660.0,cm-pad_resize,bg-000000,fo-top:l-text,ie-RnJpLCAxNCBBdWcgb253YXJkcw%3D%3D,fs-29,co-FFFFFF,ly-612,lx-24,pa-8_0_0_0,l-end:l-image,i-discovery-catalog@@icons@@pt-v1.png,t-false,lfo-top_right,lx-N5,ly-0,w-160,l-end/et00376688-qeunduylbz-portrait.jpg",
    "time": "",
    "duration": "3 Hour",
    "language": "Hindi, Marathi",
    "genre": ""
  },
  {
    "title": "Gagan Damama Bajiyo",
    "date": "Fri, 14 Aug",
    "venue": "Shri Ram Centre for Performing Arts: Delhi",
    "price": "149",
    "genreLine": "Hindi/English",
    "link": "https://in.bookmyshow.com/plays/gagan-damama-bajiyo/ET00506178",
    "image": "https://assets-in.bmscdn.com/discovery-catalog/events/tr:w-400,h-600,bg-CCCCCC,e-usm-2-2-0.5-0.008:w-400.0,h-660.0,cm-pad_resize,bg-000000,fo-top:l-text,ie-RnJpLCAxNCBBdWc%3D,fs-29,co-FFFFFF,ly-612,lx-24,pa-8_0_0_0,l-end/et00506178-yxjbkmfpar-portrait.jpg",
    "time": "7:00 PM",
    "duration": "1 hour 50 min",
    "language": "Hindi, English",
    "genre": "Drama, Historical, Musical"
  },
  {
    "title": "Fragments in the Mirror",
    "date": "Fri, 14 Aug",
    "venue": "Akshara Theatre: Delhi",
    "price": "500",
    "genreLine": "English",
    "link": "https://in.bookmyshow.com/plays/fragments-in-the-mirror/ET00504260",
    "image": "https://assets-in.bmscdn.com/discovery-catalog/events/tr:w-400,h-600,bg-CCCCCC,e-usm-2-2-0.5-0.008:w-400.0,h-660.0,cm-pad_resize,bg-000000,fo-top:l-text,ie-RnJpLCAxNCBBdWc%3D,fs-29,co-FFFFFF,ly-612,lx-24,pa-8_0_0_0,l-end/et00504260-uhcguvyrqj-portrait.jpg",
    "time": "7:00 PM",
    "duration": "1 Hour",
    "language": "English",
    "genre": "Drama"
  },
  {
    "title": "Hi Handsome",
    "date": "Sat, 15 Aug",
    "venue": "Akshara Theatre: Delhi",
    "price": "500",
    "genreLine": "Hindustani",
    "link": "https://in.bookmyshow.com/plays/hi-handsome/ET00146892",
    "image": "https://assets-in.bmscdn.com/discovery-catalog/events/tr:w-400,h-600,bg-CCCCCC,e-usm-2-2-0.5-0.008:w-400.0,h-660.0,cm-pad_resize,bg-000000,fo-top:l-text,ie-U2F0LCAxNSBBdWc%3D,fs-29,co-FFFFFF,ly-612,lx-24,pa-8_0_0_0,l-end/et00146892-erkmfvwead-portrait.jpg",
    "time": "7:30 PM",
    "duration": "2 Hour",
    "language": "",
    "genre": "Hindustani"
  },
  {
    "title": "Mahanpur Ke Neta",
    "date": "Sat, 15 Aug",
    "venue": "Little Theatre Group (LTG) Auditorium: Delhi",
    "price": "150",
    "genreLine": "Hindustani",
    "link": "https://in.bookmyshow.com/plays/mahanpur-ke-neta/ET00489740",
    "image": "https://assets-in.bmscdn.com/discovery-catalog/events/tr:w-400,h-600,bg-CCCCCC,e-usm-2-2-0.5-0.008:w-400.0,h-660.0,cm-pad_resize,bg-000000,fo-top:l-text,ie-U2F0LCAxNSBBdWc%3D,fs-29,co-FFFFFF,ly-612,lx-24,pa-8_0_0_0,l-end/et00489740-kcyluxstpk-portrait.jpg",
    "time": "7:00 PM",
    "duration": "1 hour 40 min",
    "language": "Hindi, Marathi",
    "genre": "Hindustani"
  },
  {
    "title": "External Affairs",
    "date": "Sun, 16 Aug",
    "venue": "Shri Ram Centre for Performing Arts: Delhi",
    "price": "650",
    "genreLine": "English/Hindi",
    "link": "https://in.bookmyshow.com/plays/external-affairs/ET00445225",
    "image": "https://assets-in.bmscdn.com/discovery-catalog/events/tr:w-400,h-600,bg-CCCCCC,e-usm-2-2-0.5-0.008:w-400.0,h-660.0,cm-pad_resize,bg-000000,fo-top:l-text,ie-U3VuLCAxNiBBdWc%3D,fs-29,co-FFFFFF,ly-612,lx-24,pa-8_0_0_0,l-end/et00445225-brfedcbwcm-portrait.jpg",
    "time": "",
    "duration": "1 hour 20 min",
    "language": "Hindi, English",
    "genre": ""
  },
  {
    "title": "Blind Men's Club",
    "date": "Sun, 16 Aug",
    "venue": "Akshara Theatre: Delhi",
    "price": "500",
    "genreLine": "Hinglish",
    "link": "https://in.bookmyshow.com/plays/blind-men-s-club/ET00504253",
    "image": "https://assets-in.bmscdn.com/discovery-catalog/events/tr:w-400,h-600,bg-CCCCCC,e-usm-2-2-0.5-0.008:w-400.0,h-660.0,cm-pad_resize,bg-000000,fo-top:l-text,ie-U3VuLCAxNiBBdWc%3D,fs-29,co-FFFFFF,ly-612,lx-24,pa-8_0_0_0,l-end/et00504253-bvkavammzt-portrait.jpg",
    "time": "4:00 PM",
    "duration": "1 hour 30 min",
    "language": "",
    "genre": "Hinglish"
  },
  {
    "title": "Diary of a Madman",
    "date": "Sun, 16 Aug",
    "venue": "Akshara Theatre: Delhi",
    "price": "500",
    "genreLine": "English",
    "link": "https://in.bookmyshow.com/plays/diary-of-a-madman/ET00502435",
    "image": "https://assets-in.bmscdn.com/discovery-catalog/events/tr:w-400,h-600,bg-CCCCCC,e-usm-2-2-0.5-0.008:w-400.0,h-660.0,cm-pad_resize,bg-000000,fo-top:l-text,ie-U3VuLCAxNiBBdWc%3D,fs-29,co-FFFFFF,ly-612,lx-24,pa-8_0_0_0,l-end/et00502435-lujmsqjtle-portrait.jpg",
    "time": "7:15 PM",
    "duration": "1 hour 30 min",
    "language": "English",
    "genre": "Drama"
  },
  {
    "title": "1943 - Benaras Bluff",
    "date": "Sun, 16 Aug",
    "venue": "The Piano Man: Gurugram",
    "price": "499",
    "genreLine": "Hindi",
    "link": "https://in.bookmyshow.com/plays/1943-benaras-bluff/ET00406327",
    "image": "https://assets-in.bmscdn.com/discovery-catalog/events/tr:w-400,h-600,bg-CCCCCC,e-usm-2-2-0.5-0.008:w-400.0,h-660.0,cm-pad_resize,bg-000000,fo-top:l-text,ie-U3VuLCAxNiBBdWc%3D,fs-29,co-FFFFFF,ly-612,lx-24,pa-8_0_0_0,l-end/et00406327-ersxarebhj-portrait.jpg",
    "time": "4:00 PM",
    "duration": "1 hour 15 min",
    "language": "Hindi",
    "genre": "All age groups"
  },
  {
    "title": "Dikhai",
    "date": "Sun, 16 Aug",
    "venue": "Alliance Francaise: Delhi",
    "price": "200",
    "genreLine": "Hindi",
    "link": "https://in.bookmyshow.com/plays/dikhai/ET00504441",
    "image": "https://assets-in.bmscdn.com/discovery-catalog/events/tr:w-400,h-600,bg-CCCCCC,e-usm-2-2-0.5-0.008:w-400.0,h-660.0,cm-pad_resize,bg-000000,fo-top:l-text,ie-U3VuLCAxNiBBdWc%3D,fs-29,co-FFFFFF,ly-612,lx-24,pa-8_0_0_0,l-end/et00504441-wfrgsqfkal-portrait.jpg",
    "time": "7:15 PM",
    "duration": "1 hour 20 min",
    "language": "Hindi",
    "genre": "Drama"
  },
  {
    "title": "And Then There Were None",
    "date": "Sat, 22 Aug",
    "venue": "Akshara Theatre: Delhi",
    "price": "300",
    "genreLine": "Hindi",
    "link": "https://in.bookmyshow.com/plays/and-then-there-were-none/ET00386358",
    "image": "https://assets-in.bmscdn.com/discovery-catalog/events/tr:w-400,h-600,bg-CCCCCC,e-usm-2-2-0.5-0.008:w-400.0,h-660.0,cm-pad_resize,bg-000000,fo-top:l-text,ie-U2F0LCAyMiBBdWc%3D,fs-29,co-FFFFFF,ly-612,lx-24,pa-8_0_0_0,l-end/et00386358-fynldrcvay-portrait.jpg",
    "time": "7:00 PM",
    "duration": "1 hour 30 min",
    "language": "Hindi",
    "genre": "Drama, Mystery"
  },
  {
    "title": "Mahabharata - The Epic Tale (Revived)",
    "date": "Sat, 22 Aug onwards",
    "venue": "Mavalankar Auditorium, Constitution club of India",
    "price": "1499",
    "genreLine": "Hindi",
    "link": "https://in.bookmyshow.com/plays/mahabharata-the-epic-tale-revived/ET00399494",
    "image": "https://assets-in.bmscdn.com/discovery-catalog/events/tr:w-400,h-600,bg-CCCCCC,e-usm-2-2-0.5-0.008:w-400.0,h-660.0,cm-pad_resize,bg-000000,fo-top:l-text,ie-U2F0LCAyMiBBdWcgb253YXJkcw%3D%3D,fs-29,co-FFFFFF,ly-612,lx-24,pa-8_0_0_0,l-end/et00399494-lgmxtrtfne-portrait.jpg",
    "time": "",
    "duration": "2 hour",
    "language": "Hindi",
    "genre": ""
  },
  {
    "title": "Window Tak AAshiqui",
    "date": "Sat, 22 Aug",
    "venue": "Shri Ram Centre for Performing Arts: Delhi",
    "price": "600",
    "genreLine": "Hindi",
    "link": "https://in.bookmyshow.com/plays/window-tak-aashiqui/ET00490447",
    "image": "https://assets-in.bmscdn.com/discovery-catalog/events/tr:w-400,h-600,bg-CCCCCC,e-usm-2-2-0.5-0.008:w-400.0,h-660.0,cm-pad_resize,bg-000000,fo-top:l-text,ie-U2F0LCAyMiBBdWc%3D,fs-29,co-FFFFFF,ly-612,lx-24,pa-8_0_0_0,l-end/et00490447-vnrmferszx-portrait.jpg",
    "time": "",
    "duration": "1 hour 30 min",
    "language": "Hindi, Marathi",
    "genre": ""
  },
  {
    "title": "Guilty! My Lord",
    "date": "Sat, 22 Aug",
    "venue": "Alliance Francaise: Delhi",
    "price": "250",
    "genreLine": "Hindi",
    "link": "https://in.bookmyshow.com/plays/guilty-my-lord/ET00503991",
    "image": "https://assets-in.bmscdn.com/discovery-catalog/events/tr:w-400,h-600,bg-CCCCCC,e-usm-2-2-0.5-0.008:w-400.0,h-660.0,cm-pad_resize,bg-000000,fo-top:l-text,ie-U2F0LCAyMiBBdWc%3D,fs-29,co-FFFFFF,ly-612,lx-24,pa-8_0_0_0,l-end/et00503991-abklewctxn-portrait.jpg",
    "time": "7:00 PM",
    "duration": "1 hour 30 min",
    "language": "Hindi",
    "genre": "Drama"
  },
  {
    "title": "Ilhaam",
    "date": "Sun, 23 Aug",
    "venue": "Blank Canvas: New Delhi",
    "price": "200",
    "genreLine": "Hindi",
    "link": "https://in.bookmyshow.com/plays/ilhaam-by-manav-kaul/ET00451474",
    "image": "https://assets-in.bmscdn.com/discovery-catalog/events/tr:w-400,h-600,bg-CCCCCC,e-usm-2-2-0.5-0.008:w-400.0,h-660.0,cm-pad_resize,bg-000000,fo-top:l-text,ie-U3VuLCAyMyBBdWc%3D,fs-29,co-FFFFFF,ly-612,lx-24,pa-8_0_0_0,l-end/et00451474-dxfptlfvkb-portrait.jpg",
    "time": "6:15 PM",
    "duration": "1 Hour",
    "language": "Hindi",
    "genre": "Drama"
  },
  {
    "title": "PARK - MANAV KAUL",
    "date": "Sun, 23 Aug",
    "venue": "Blank Canvas: New Delhi",
    "price": "200",
    "genreLine": "Hindi",
    "link": "https://in.bookmyshow.com/plays/park/ET00416118",
    "image": "https://assets-in.bmscdn.com/discovery-catalog/events/tr:w-400,h-600,bg-CCCCCC,e-usm-2-2-0.5-0.008:w-400.0,h-660.0,cm-pad_resize,bg-000000,fo-top:l-text,ie-U3VuLCAyMyBBdWc%3D,fs-29,co-FFFFFF,ly-612,lx-24,pa-8_0_0_0,l-end/et00416118-jlpwrmypjc-portrait.jpg",
    "time": "7:30 PM",
    "duration": "1 hour 20 min",
    "language": "Hindi",
    "genre": "Drama"
  },
  {
    "title": "Amrita Pritam - Pinjar",
    "date": "Sat, 29 Aug",
    "venue": "Little Theatre Group (LTG) Auditorium: Delhi",
    "price": "200",
    "genreLine": "Hindi/Urdu",
    "link": "https://in.bookmyshow.com/plays/amrita-pritam-pinjar/ET00397397",
    "image": "https://assets-in.bmscdn.com/discovery-catalog/events/tr:w-400,h-600,bg-CCCCCC,e-usm-2-2-0.5-0.008:w-400.0,h-660.0,cm-pad_resize,bg-000000,fo-top:l-text,ie-U2F0LCAyOSBBdWc%3D,fs-29,co-FFFFFF,ly-612,lx-24,pa-8_0_0_0,l-end/et00397397-vsbvckghlw-portrait.jpg",
    "time": "7:00 PM",
    "duration": "1 hour 45 min",
    "language": "Hindi, Urdu",
    "genre": "Drama, Historical"
  },
  {
    "title": "State v/s Manto: In the court of Manto",
    "date": "Sat, 29 Aug",
    "venue": "Little Theatre Group (LTG) Auditorium: Delhi",
    "price": "200",
    "genreLine": "Hindi/Urdu",
    "link": "https://in.bookmyshow.com/plays/state-v-s-manto-in-the-court-of-manto/ET00396787",
    "image": "https://assets-in.bmscdn.com/discovery-catalog/events/tr:w-400,h-600,bg-CCCCCC,e-usm-2-2-0.5-0.008:w-400.0,h-660.0,cm-pad_resize,bg-000000,fo-top:l-text,ie-U2F0LCAyOSBBdWc%3D,fs-29,co-FFFFFF,ly-612,lx-24,pa-8_0_0_0,l-end/et00396787-fuatcvwjuh-portrait.jpg",
    "time": "4:30 PM",
    "duration": "1 hour 30 min",
    "language": "Hindi, Urdu",
    "genre": "Drama"
  },
  {
    "title": "khamosh! adalat jari hai",
    "date": "Sun, 30 Aug",
    "venue": "Akshara Theatre: Delhi",
    "price": "200",
    "genreLine": "Hindi",
    "link": "https://in.bookmyshow.com/plays/khamosh-adalat-jari-hai/ET00369648",
    "image": "https://assets-in.bmscdn.com/discovery-catalog/events/tr:w-400,h-600,bg-CCCCCC,e-usm-2-2-0.5-0.008:w-400.0,h-660.0,cm-pad_resize,bg-000000,fo-top:l-text,ie-U3VuLCAzMCBBdWc%3D,fs-29,co-FFFFFF,ly-612,lx-24,pa-8_0_0_0,l-end/et00369648-tknxtvlgnk-portrait.jpg",
    "time": "7:15 PM",
    "duration": "1 hour 50 min",
    "language": "Hindi",
    "genre": "Drama"
  },
  {
    "title": "Peele Scooter Wala Aadmi",
    "date": "Sun, 30 Aug",
    "venue": "Akshara Theatre: Delhi",
    "price": "250",
    "genreLine": "Hindi",
    "link": "https://in.bookmyshow.com/plays/peele-scooter-wala-aadmi/ET00444010",
    "image": "https://assets-in.bmscdn.com/discovery-catalog/events/tr:w-400,h-600,bg-CCCCCC,e-usm-2-2-0.5-0.008:w-400.0,h-660.0,cm-pad_resize,bg-000000,fo-top:l-text,ie-U3VuLCAzMCBBdWc%3D,fs-29,co-FFFFFF,ly-612,lx-24,pa-8_0_0_0,l-end/et00444010-ykgrkcxnmj-portrait.jpg",
    "time": "6:00 PM",
    "duration": "1 hour 10 min",
    "language": "Hindi",
    "genre": "Drama"
  },
  {
    "title": "Bali Aur Shambhu",
    "date": "Sun, 30 Aug",
    "venue": "Akshara Theatre: Delhi",
    "price": "250",
    "genreLine": "Hindi",
    "link": "https://in.bookmyshow.com/plays/bali-aur-shambhu/ET00418256",
    "image": "https://assets-in.bmscdn.com/discovery-catalog/events/tr:w-400,h-600,bg-CCCCCC,e-usm-2-2-0.5-0.008:w-400.0,h-660.0,cm-pad_resize,bg-000000,fo-top:l-text,ie-U3VuLCAzMCBBdWc%3D,fs-29,co-FFFFFF,ly-612,lx-24,pa-8_0_0_0,l-end/et00418256-gapubyvbrj-portrait.jpg",
    "time": "4:00 PM",
    "duration": "1 hour 20 min",
    "language": "Hindi",
    "genre": "Drama"
  },
  {
    "title": "Bahot Bada Sawal",
    "date": "Sun, 30 Aug",
    "venue": "Akshara Theatre: Delhi",
    "price": "200",
    "genreLine": "Hindi",
    "link": "https://in.bookmyshow.com/plays/bahot-bada-sawal/ET00503166",
    "image": "https://assets-in.bmscdn.com/discovery-catalog/events/tr:w-400,h-600,bg-CCCCCC,e-usm-2-2-0.5-0.008:w-400.0,h-660.0,cm-pad_resize,bg-000000,fo-top:l-text,ie-U3VuLCAzMCBBdWc%3D,fs-29,co-FFFFFF,ly-612,lx-24,pa-8_0_0_0,l-end/et00503166-gvacnytner-portrait.jpg",
    "time": "2:30 PM",
    "duration": "45 Min",
    "language": "Hindi",
    "genre": "Drama"
  },
  {
    "title": "'Chakravyuh' featuring Nitish Bharadwaj as Krishna",
    "date": "Sat, 5 Sep",
    "venue": "Kamani Auditorium: Delhi",
    "price": "600",
    "genreLine": "Hindi",
    "link": "https://in.bookmyshow.com/plays/chakravyuh-featuring-nitish-bharadwaj-as-krishna/ET00409743",
    "image": "https://assets-in.bmscdn.com/discovery-catalog/events/tr:w-400,h-600,bg-CCCCCC,e-usm-2-2-0.5-0.008:w-400.0,h-660.0,cm-pad_resize,bg-000000,fo-top:l-text,ie-U2F0LCA1IFNlcA%3D%3D,fs-29,co-FFFFFF,ly-612,lx-24,pa-8_0_0_0,l-end/et00409743-jpcvrxamel-portrait.jpg",
    "time": "",
    "duration": "1 hour 40 min",
    "language": "Hindi, Marathi",
    "genre": ""
  },
  {
    "title": "Kahanibaaz By Ashish Vidyarthi",
    "date": "Sun, 6 Sep",
    "venue": "Aiwan-E-Ghalib Auditorium: Delhi",
    "price": "499",
    "genreLine": "Hindi",
    "link": "https://in.bookmyshow.com/plays/kahanibaaz-by-ashish-vidyarthi/ET00500942",
    "image": "https://assets-in.bmscdn.com/discovery-catalog/events/tr:w-400,h-600,bg-CCCCCC,e-usm-2-2-0.5-0.008:w-400.0,h-660.0,cm-pad_resize,bg-000000,fo-top:l-text,ie-U3VuLCA2IFNlcA%3D%3D,fs-29,co-FFFFFF,ly-612,lx-24,pa-8_0_0_0,l-end/et00500942-ekhbttwsav-portrait.jpg",
    "time": "8:00 PM",
    "duration": "1 hour 30 min",
    "language": "Hindi",
    "genre": "Comedy"
  },
  {
    "title": "Pandit Ki Daud M.....Tak",
    "date": "Sat, 12 Sep",
    "venue": "Lilanoor Center: New Delhi",
    "price": "500",
    "genreLine": "Hindi",
    "link": "https://in.bookmyshow.com/plays/pandit-ki-daud-m-tak/ET00497924",
    "image": "https://assets-in.bmscdn.com/discovery-catalog/events/tr:w-400,h-600,bg-CCCCCC,e-usm-2-2-0.5-0.008:w-400.0,h-660.0,cm-pad_resize,bg-000000,fo-top:l-text,ie-U2F0LCAxMiBTZXA%3D,fs-29,co-FFFFFF,ly-612,lx-24,pa-8_0_0_0,l-end/et00497924-afqekuqthr-portrait.jpg",
    "time": "7:30 PM",
    "duration": "1 hour 20 min",
    "language": "Hindi",
    "genre": "Drama, Political"
  },
  {
    "title": "Farewell : An Entropy of Separation",
    "date": "Sun, 13 Sep",
    "venue": "Shri Ram Centre for Performing Arts: Delhi",
    "price": "249",
    "genreLine": "Hindi",
    "link": "https://in.bookmyshow.com/plays/farewell-an-entropy-of-separation/ET00502807",
    "image": "https://assets-in.bmscdn.com/discovery-catalog/events/tr:w-400,h-600,bg-CCCCCC,e-usm-2-2-0.5-0.008:w-400.0,h-660.0,cm-pad_resize,bg-000000,fo-top:l-text,ie-U3VuLCAxMyBTZXA%3D,fs-29,co-FFFFFF,ly-612,lx-24,pa-8_0_0_0,l-end/et00502807-rllgwsxdfu-portrait.jpg",
    "time": "4:00 PM",
    "duration": "2 Hour",
    "language": "Hindi",
    "genre": "Drama"
  },
  {
    "title": "Kahaniyan Sunaata Hun",
    "date": "Sun, 13 Sep",
    "venue": "Aiwan-E-Ghalib Auditorium: Delhi",
    "price": "499",
    "genreLine": "Hindi",
    "link": "https://in.bookmyshow.com/plays/kahaniyan-sunaata-hu/ET00503256",
    "image": "https://assets-in.bmscdn.com/discovery-catalog/events/tr:w-400,h-600,bg-CCCCCC,e-usm-2-2-0.5-0.008:w-400.0,h-660.0,cm-pad_resize,bg-000000,fo-top:l-text,ie-U3VuLCAxMyBTZXA%3D,fs-29,co-FFFFFF,ly-612,lx-24,pa-8_0_0_0,l-end/et00503256-jwytyjtetx-portrait.jpg",
    "time": "8:00 PM",
    "duration": "2 Hour",
    "language": "Hindi",
    "genre": "Classic, Romantic"
  },
  {
    "title": "Kahaniyan Sunaata Hun By Neelesh Misra",
    "date": "Sun, 13 Sep",
    "venue": "Multiple Venues",
    "price": "499",
    "genreLine": "Hindi",
    "link": "https://in.bookmyshow.com/plays/kahaniyan-sunaata-hun-by-neelesh-misra/ET00504180",
    "image": "https://assets-in.bmscdn.com/discovery-catalog/events/tr:w-400,h-600,bg-CCCCCC,e-usm-2-2-0.5-0.008:w-400.0,h-660.0,cm-pad_resize,bg-000000,fo-top:l-text,ie-U3VuLCAxMyBTZXA%3D,fs-29,co-FFFFFF,ly-612,lx-24,pa-8_0_0_0,l-end:l-image,i-discovery-catalog@@icons@@bundle-icon-shadow-4x.png,lx-15,ly-15,w-50,l-end/et00504180-ufpjxyyycq-portrait.jpg",
    "time": "",
    "duration": "2 Hour",
    "language": "Hindi",
    "genre": ""
  },
  {
    "title": "Aapke Apne Aapke Baad",
    "date": "Sat, 19 Sep",
    "venue": "Lok Kala Manch: New Delhi",
    "price": "199",
    "genreLine": "Hindi/English",
    "link": "https://in.bookmyshow.com/plays/aapke-apne-aapke-baad/ET00502407",
    "image": "https://assets-in.bmscdn.com/discovery-catalog/events/tr:w-400,h-600,bg-CCCCCC,e-usm-2-2-0.5-0.008:w-400.0,h-660.0,cm-pad_resize,bg-000000,fo-top:l-text,ie-U2F0LCAxOSBTZXA%3D,fs-29,co-FFFFFF,ly-612,lx-24,pa-8_0_0_0,l-end/et00502407-axfvyvrwuu-portrait.jpg",
    "time": "7:00 PM",
    "duration": "1 hour 15 min",
    "language": "Hindi, English",
    "genre": "Comedy, Contemporary, Drama"
  },
  {
    "title": "Traasadi BY MANAV KAUL",
    "date": "Sat, 26 Sep",
    "venue": "Little Theatre Group (LTG) Auditorium: Delhi",
    "price": "599",
    "genreLine": "Hindi",
    "link": "https://in.bookmyshow.com/plays/traasadi-by-manav-kaul/ET00467785",
    "image": "https://assets-in.bmscdn.com/discovery-catalog/events/tr:w-400,h-600,bg-CCCCCC,e-usm-2-2-0.5-0.008:w-400.0,h-660.0,cm-pad_resize,bg-000000,fo-top:l-text,ie-U2F0LCAyNiBTZXA%3D,fs-29,co-FFFFFF,ly-612,lx-24,pa-8_0_0_0,l-end/et00467785-xmmsknuutf-portrait.jpg",
    "time": "5:00 PM",
    "duration": "1 hour 10 min",
    "language": "Hindi",
    "genre": "Drama"
  },
  {
    "title": "Toba Tek Singh",
    "date": "Sun, 27 Sep",
    "venue": "Akshara Theatre: Delhi",
    "price": "250",
    "genreLine": "Hindi",
    "link": "https://in.bookmyshow.com/plays/toba-tek-singh/ET00441021",
    "image": "https://assets-in.bmscdn.com/discovery-catalog/events/tr:w-400,h-600,bg-CCCCCC,e-usm-2-2-0.5-0.008:w-400.0,h-660.0,cm-pad_resize,bg-000000,fo-top:l-text,ie-U3VuLCAyNyBTZXA%3D,fs-29,co-FFFFFF,ly-612,lx-24,pa-8_0_0_0,l-end/et00441021-vpavnekgju-portrait.jpg",
    "time": "6:00 PM",
    "duration": "1 hour 10 min",
    "language": "Hindi",
    "genre": "Drama"
  },
  {
    "title": "THE ROOM OF MEMORIES",
    "date": "Sat, 17 Oct onwards",
    "venue": "Kamani Auditorium: Delhi",
    "price": "999",
    "genreLine": "English",
    "link": "https://in.bookmyshow.com/plays/the-room-of-memories/ET00453270",
    "image": "https://assets-in.bmscdn.com/discovery-catalog/events/tr:w-400,h-600,bg-CCCCCC,e-usm-2-2-0.5-0.008:w-400.0,h-660.0,cm-pad_resize,bg-000000,fo-top:l-text,ie-U2F0LCAxNyBPY3Qgb253YXJkcw%3D%3D,fs-29,co-FFFFFF,ly-612,lx-24,pa-8_0_0_0,l-end/et00453270-zturwtfpsc-portrait.jpg",
    "time": "7:30 PM",
    "duration": "1 hour 15 min",
    "language": "English",
    "genre": "Adventure, Comedy, Musical"
  },
  {
    "title": "Ek Shaam, Ek Script",
    "date": "Sat, 28 Nov",
    "venue": "Gate No. 1 Lodhi Garden: Delhi",
    "price": "299",
    "genreLine": "Hindi/English",
    "link": "https://in.bookmyshow.com/plays/ek-shaam-ek-script/ET00487301",
    "image": "https://assets-in.bmscdn.com/discovery-catalog/events/tr:w-400,h-600,bg-CCCCCC,e-usm-2-2-0.5-0.008:w-400.0,h-660.0,cm-pad_resize,bg-000000,fo-top:l-text,ie-U2F0LCAyOCBOb3Y%3D,fs-29,co-FFFFFF,ly-612,lx-24,pa-8_0_0_0,l-end/et00487301-lnlwdkwvbx-portrait.jpg",
    "time": "6:15 PM",
    "duration": "1 hour 30 min",
    "language": "Hindi, English",
    "genre": "Adult, Classic, Drama"
  }
]